Workbook

Sheet Cronograma de Pesquisa em Revis
A1: Fase | B1: Atividade / Tarefa | C1: Detalhes & Entregáveis | D1: Início | E1: Prazo Estimado | F1: Data Finalização | G1: Comentário
A2: 0. Prep. | B2: Padronização de Dados | C2: Limpeza da tabela Excel: Unificar nomes de países, técnicas (ex: "Bi-LSTM" = "LSTM") e métricas. | D2: 46057 | E2: 46057
A3: 1. Metod. | B3: Diagrama de Venn | C3: Gerar gráfico de sobreposição entre Google Scholar e IJDSA. | D3: 46058 | E3: 46058 | F3: 46063 | G3: Meus dados não têm sobreposição (1_Sobreposição)
A4: 1. Metod. | B4: Fluxo PRISMA | C4: Finalizar diagrama com números exatos de exclusão (Triagem -> Inclusão).+1 | D4: 46058 | E4: 46058 | F4: 46063
A5: 1. Metod. | B5: Nuvem de Palavras | C5: Extrair textos dos Resumos (Abstracts) e gerar nuvem para validar alinhamento. | D5: 46059 | E5: 46059 | F5: 46073
A6: 2. Biblio. | B6: Pareto de Publicações | C6: Gráfico de barras: Revistas/Conferências por contagem (identificar o "Top Tier"). | D6: 46062 | E6: 46062 | F6: 46073
A7: 2. Biblio. | B7: Mapa Geo-Linguístico | C7: Cruzamento: País dos Autores vs. Idioma do Dataset (focar no viés anglocêntrico). | D7: 46063 | E7: 46063 | F7: 46073
A8: 2. Biblio. | B8: Matriz de Domínios | C8: Heatmap: Domínio (ex: Finanças) x Target (ex: Preço, Volatilidade). | D8: 46064 | E8: 46064 | F8: 46073
A9: 3. Técnica | B9: Heatmap Co-ocorrência | C9: Matriz: Método de Extração (linhas) x Modelo de Regressão (colunas). | D9: 46065 | E9: 46065 | F9: 46073
A10: 3. Técnica | B10: Scatter "Data Hunger" | C10: Gráfico: Tamanho do Dataset (Log N) vs. Categoria NLP (Dense vs. Contextual). | D10: 46066 | E10: 46066
A11: 3. Técnica | B11: Escrita Teórica (P1) | C11: Redação da fundamentação técnica: Técnica #1 (ex: Transformers/BERT). | D11: 46069 | E11: 46069
A12: 3. Técnica | B12: Escrita Teórica (P2) | C12: Redação da fundamentação técnica: Técnica #2 e #3 (ex: SVR, LSTM). | D12: 46070 | E12: 46070
A13: 4. Perf. | B13: Auditoria de Métricas | C13: Tabela de frequência: Quais métricas são usadas? (Crise de padronização) . | D13: 46071 | E13: 46071
A14: 4. Perf. | B14: Cálculo Ganho Relativo | C14: Calcular % de melhoria sobre baseline para cada paper (Tarefa complexa - Parte 1). | D14: 46072 | E14: 46072
A15: 4. Perf. | B15: Cálculo Ganho Relativo | C15: Calcular % de melhoria sobre baseline (Parte 2) + Consolidar gráfico. | D15: 46073 | E15: 46073
A16: 4. Perf. | B16: Clusterização & Tabela | C16: Tabela de Benchmarks agrupada por Domínio (ex: Tabela "Finanças" com MAPE). | D16: 46076 | E16: 46076
A17: 5. Quali. | B17: Tagging (Vant./Limit.) | C17: Ler colunas de texto e criar tags (categorias) para Vantagens e Limitações. | D17: 46077 | E17: 46077
A18: 5. Quali. | B18: Gráficos Qualitativos | C18: Gerar gráficos de barras das tags (ex: "Overfitting" como limitação comum). | D18: 46078 | E18: 46078
A19: 5. Quali. | B19: Contribuição & Inov. | C19: Mapear tipo de contribuição (Nova Arquitetura vs. Nova Aplicação). | D19: 46079 | E19: 46079
A20: Escrita | B20: Síntese dos Resultados | C20: Redação do capítulo de Resultados (unindo os gráficos gerados). | D20: 46080 | E20: 46080
A21: Escrita | B21: Discussão Crítica | C21: Redação da Discussão (focando em Trade-offs, Gaps e Vieses). | D21: 46083 | E21: 46083
... A25: Fim | B25: Marco Final | C25: Versão pronta para submissão/apresentação ao orientador. | D25: 46087 | E25: 46087

Sheet 1_Sobreposição
A1: title | B1: source
A2: <i>SeNSe</i>: embedding alignment via semantic anchors selection | B2: Google Scholar
A3: A MultilingualBERT EmbeddingsApproach in Identifying Factors Influencing Employability Among Pre-University Students
A4: A Pretraining Approach for Small-sample Training Employing Radiographs (PASTER): a Multimodal Transformer Trained by Chest Radiography and Free-text Reports | B4: Google Scholar
A5: A Survey on the Impact of Pre-Trained Language Models in Sentiment Classification Task | B5: Springer International Journal of Data Science and Analytics
A6: A common-specific feature cross-fusion attention mechanism for KGVQA | B6: Springer International Journal of Data Science and Analytics
A7: A comparative study ontf-idffeature weighting method and its analysis using unstructured dataset | B7: Google Scholar
A8: A deep learning-based approach for identifying unresolved questions on Stack Exchange Q &amp;A communities through graph-based communication modelling | B8: Springer International Journal of Data Science and Analytics
A9: A detailed analysis into evaluation metrics for knowledge graph evaluation | B9: Springer International Journal of Data Science and Analytics
A10: A detailed review on word embedding techniques with emphasis onword2vec | B10: Google Scholar
A11: A graph neural network-based machine learning model for sentiment polarity and behavior identification of COVID patients | B11: Springer International Journal of Data Science and Analytics
A12: A hybrid deep learning neural network for early plant disease diagnosis using a real-world Wheat–Barley vision dataset: challenges and solutions | B12: Springer International Journal of Data Science and Analytics
A13: A hybrid framework for fake news detection using transformer models with MASHAP | B13: Springer International Journal of Data Science and Analytics
A14: A hybrid self attentive linearized phrase structured transformer based RNN for financial sentence analysis with sentence level explainability | B14: Google Scholar
A15: A late fusion framework using whale optimization technique and attention-BiLSTM for fake news detection | B15: Springer International Journal of Data Science and Analytics
... A201: … SemEval-2024 Task 1: Evaluating Semantic Textual Relatedness in Low-resource Languages using Various Embedding Methods and Machine LearningRegression… | B201: Google Scholar

Sheet 2_Prisma
A1: index | B1: title | C1: link | D1: year | E1: citations | F1: pdf_link | G1: source | H1: category | I1: qtd | J1: Abstract read | K1: Includes Feature extraction | L1: Text as regression model variables | M1: No mention of regression | N1: No mention of using NLP for supervised Machine Learning | O1: NLP nor Regression are mentioned | P1: Revisto para nova rejeição | Q1: Rejeição nova: "O estudo aborda a tarefa como um problema de classificação (saídas discretas/classes) em vez de regressão (saídas numéricas contínuas)." | R1: Duplicado | S1: Sem acesso | T1: Etapa | V1: Item | W1: Descrição | X1: Total | Y1: Springer International Journal of Data Science and Analytics | Z1: Google Scholar | AB1: =SUM(I:I) -> 291 | AC1: =SUMIFS($I:$I,$G:$G,Y1) -> 172 | AD1: =SUMIFS($I:$I,$G:$G,Z1) -> 119
A2: 1 | B2: <i>SeNSe</i>: embedding alignment via semantic anchors selection | C2: https://link.springer.com/article/10.1007/s41060-024-00522-z | D2: 2024 | E2: -1 | F2: None | G2: Springer International Journal of Data Science and Analytics | H2: ['Dense Embeddings', 'Applied cases'] | I2: =LEN(H2)-LEN(SUBSTITUTE(H2,",",""))+1 -> 2 | J2: TRUE | K2: FALSE | L2: FALSE | M2: TRUE | N2: TRUE | O2: FALSE | T2: =IFERROR(IFS(K2=FALSE,"IC III",L2=FALSE,"IC IV",M2=TRUE,"EC I",N2=TRUE,"EC II",O2=TRUE,"EC III",R2>0,"EC IV",Q2=TRUE,"EC V",S2<>"","SA"),"OK") -> IC III | V2: IC III | W2: Artigos que aplicam ou descrevem métodos de extração de características textuais. | X2: =SUMIFS(I:I,T:T,V2) -> 49 | Y2: =SUMIFS($I:$I,$T:$T,$V2,$G:$G,Y$1) -> 40 | Z2: =SUMIFS($I:$I,$T:$T,$V2,$G:$G,Z$1) -> 9 | AB2: =AB1-X2 -> 242 | AC2: =AC1-Y2 -> 132 | AD2: =AD1-Z2 -> 110
A3: =A2+1 -> 2 | B3: A MultilingualBERT EmbeddingsApproach in Identifying Factors Influencing Employability Among Pre-University Students | C3: https://ieeexplore.ieee.org/abstract/document/10730172/ | D3: 2024 | E3: 2 | F3: nan | G3: Google Scholar | H3: ['Contextual Embeddings'] | I3: =LEN(H3)-LEN(SUBSTITUTE(H3,",",""))+1 -> 1 | J3: TRUE | K3: TRUE | L3: TRUE | M3: FALSE | N3: FALSE | O3: FALSE | P3: TRUE | Q3: TRUE | T3: =IFERROR(IFS(K3=FALSE,"IC III",L3=FALSE,"IC IV",M3=TRUE,"EC I",N3=TRUE,"EC II",O3=TRUE,"EC III",R3>0,"EC IV",Q3=TRUE,"EC V",S3<>"","SA"),"OK") -> EC V | V3: IC IV | W3: Artigos que usam texto como variável para modelos de regressão. | X3: =SUMIFS(I:I,T:T,V3) -> 192 | Y3: =SUMIFS($I:$I,$T:$T,$V3,$G:$G,Y$1) -> 120 | Z3: =SUMIFS($I:$I,$T:$T,$V3,$G:$G,Z$1) -> 72 | AB3: =AB2-X3 -> 50 | AC3: =AC2-Y3 -> 12 | AD3: =AD2-Z3 -> 38
A4: =A3+1 -> 3 | B4: A Pretraining Approach for Small-sample Training Employing Radiographs (PASTER): a Multimodal Transformer Trained by Chest Radiography and Free-text Reports | C4: https://link.springer.com/article/10.1007/s10916-025-02263-3 | D4: 2025 | E4: 1 | F4: https://linchin.ndmctsgh.edu.tw/papers/2025/2025%20Journal%20of%20Medical%20System.%2049(1)%20120%20(cor).pdf | G4: Google Scholar | H4: ['Contextual Embeddings'] | I4: =LEN(H4)-LEN(SUBSTITUTE(H4,",",""))+1 -> 1 | J4: TRUE | K4: TRUE | L4: TRUE | M4: FALSE | N4: FALSE | O4: FALSE | P4: TRUE | Q4: TRUE | T4: =IFERROR(IFS(K4=FALSE,"IC III",L4=FALSE,"IC IV",M4=TRUE,"EC I",N4=TRUE,"EC II",O4=TRUE,"EC III",R4>0,"EC IV",Q4=TRUE,"EC V",S4<>"","SA"),"OK") -> EC V | V4: EC I | W4: Trabalhos sem aplicação direta em modelos de regressão. | X4: =SUMIFS(I:I,T:T,V4) -> 1 | Y4: =SUMIFS($I:$I,$T:$T,$V4,$G:$G,Y$1) -> 1 | Z4: =SUMIFS($I:$I,$T:$T,$V4,$G:$G,Z$1) -> 0 | AB4: =AB3-X4 -> 49 | AC4: =AC3-Y4 -> 11 | AD4: =AD3-Z4 -> 38
A5: =A4+1 -> 4 | B5: A Survey on the Impact of Pre-Trained Language Models in Sentiment Classification Task | C5: https://link.springer.com/article/10.1007/s41060-025-00805-z | D5: 2025 | E5: -1 | F5: None | G5: Springer International Journal of Data Science and Analytics | H5: ['Classic Methods', 'Dense Embeddings', 'Comparison of methods', 'Literature Reviews', 'Applied cases'] | I5: =LEN(H5)-LEN(SUBSTITUTE(H5,",",""))+1 -> 5 | J5: TRUE | K5: TRUE | L5: FALSE | M5: TRUE | N5: FALSE | O5: FALSE | T5: =IFERROR(IFS(K5=FALSE,"IC III",L5=FALSE,"IC IV",M5=TRUE,"EC I",N5=TRUE,"EC II",O5=TRUE,"EC III",R5>0,"EC IV",Q5=TRUE,"EC V",S5<>"","SA"),"OK") -> IC IV | V5: EC II | W5: Artigos puramente teóricos de NLP sem relação com representação de texto para machine learning supervisionado. | X5: =SUMIFS(I:I,T:T,V5) -> 0 | Y5: =SUMIFS($I:$I,$T:$T,$V5,$G:$G,Y$1) -> 0 | Z5: =SUMIFS($I:$I,$T:$T,$V5,$G:$G,Z$1) -> 0 | AB5: =AB4-X5 -> 49 | AC5: =AC4-Y5 -> 11 | AD5: =AD4-Z5 -> 38
A6: =A5+1 -> 5 | B6: A common-specific feature cross-fusion attention mechanism for KGVQA | C6: https://link.springer.com/article/10.1007/s41060-024-00536-7 | D6: 2024 | E6: -1 | F6: None | G6: Springer International Journal of Data Science and Analytics | H6: ['Dense Embeddings', 'Comparison of methods'] | I6: =LEN(H6)-LEN(SUBSTITUTE(H6,",",""))+1 -> 2 | J6: TRUE | K6: TRUE | L6: FALSE | M6: TRUE | N6: FALSE | O6: FALSE | T6: =IFERROR(IFS(K6=FALSE,"IC III",L6=FALSE,"IC IV",M6=TRUE,"EC I",N6=TRUE,"EC II",O6=TRUE,"EC III",R6>0,"EC IV",Q6=TRUE,"EC V",S6<>"","SA"),"OK") -> IC IV | V6: EC III | W6: Não há menção de NLP e nem regressão no texto. | X6: =SUMIFS(I:I,T:T,V6) -> 0 | Y6: =SUMIFS($I:$I,$T:$T,$V6,$G:$G,Y$1) -> 0 | Z6: =SUMIFS($I:$I,$T:$T,$V6,$G:$G,Z$1) -> 0 | AB6: =AB5-X6 -> 49 | AC6: =AC5-Y6 -> 11 | AD6: =AD5-Z6 -> 38
A7: =A6+1 -> 6 | B7: A comparative study ontf-idffeature weighting method and its analysis using unstructured dataset | C7: https://arxiv.org/abs/2308.04037 | D7: 2023 | E7: 120 | F7: https://arxiv.org/pdf/2308.04037 | G7: Google Scholar | H7: ['Classic Methods'] | I7: =LEN(H7)-LEN(SUBSTITUTE(H7,",",""))+1 -> 1 | J7: TRUE | K7: TRUE | L7: TRUE | M7: FALSE | N7: FALSE | O7: FALSE | P7: TRUE | Q7: TRUE | T7: =IFERROR(IFS(K7=FALSE,"IC III",L7=FALSE,"IC IV",M7=TRUE,"EC I",N7=TRUE,"EC II",O7=TRUE,"EC III",R7>0,"EC IV",Q7=TRUE,"EC V",S7<>"","SA"),"OK") -> EC V | V7: EC IV | W7: Estudos duplicados. | X7: =SUMIFS(I:I,T:T,V7)+SUM(X13:X15) -> 8 | Y7: =SUMIFS($I:$I,$T:$T,$V7,$G:$G,Y$1)+sum(Y13:Y15) -> 5 | Z7: =SUMIFS($I:$I,$T:$T,$V7,$G:$G,Z$1)+SUM(Z13:Z15) -> 3 | AB7: =AB6-X7 -> 41 | AC7: =AC6-Y7 -> 6 | AD7: =AD6-Z7 -> 35
A8: =A7+1 -> 7 | B8: A deep learning-based approach for identifying unresolved questions on Stack Exchange Q &amp;A communities through graph-based communication modelling | C8: https://link.springer.com/article/10.1007/s41060-023-00454-0 | D8: 2023 | E8: -1 | F8: None | G8: Springer International Journal of Data Science and Analytics | H8: ['Contextual Embeddings'] | I8: =LEN(H8)-LEN(SUBSTITUTE(H8,",",""))+1 -> 1 | J8: TRUE | K8: TRUE | L8: FALSE | M8: TRUE | N8: FALSE | O8: TRUE | T8: =IFERROR(IFS(K8=FALSE,"IC III",L8=FALSE,"IC IV",M8=TRUE,"EC I",N8=TRUE,"EC II",O8=TRUE,"EC III",R8>0,"EC IV",Q8=TRUE,"EC V",S8<>"","SA"),"OK") -> IC IV | V8: EC V | W8: O estudo aborda a tarefa como um problema de classificação (saídas discretas/classes) em vez de regressão (saídas numéricas contínuas). | X8: =COUNTIFS(T:T,V8) -> 15 | Y8: =COUNTIFS($T:$T,$V8,$G:$G,Y$1) -> 3 | Z8: =COUNTIFS($T:$T,$V8,$G:$G,Z$1) -> 12 | AB8: =AB7-X8 -> 26 | AC8: =AC7-Y8 -> 3 | AD8: =AD7-Z8 -> 23
A9: =A8+1 -> 8 | B9: A detailed analysis into evaluation metrics for knowledge graph evaluation | C9: https://link.springer.com/article/10.1007/s41060-025-00871-3 | D9: 2025 | E9: -1 | F9: None | G9: Springer International Journal of Data Science and Analytics | H9: ['Applied cases'] | I9: =LEN(H9)-LEN(SUBSTITUTE(H9,",",""))+1 -> 1 | J9: TRUE | K9: FALSE | L9: FALSE | M9: TRUE | N9: FALSE | O9: TRUE | T9: =IFERROR(IFS(K9=FALSE,"IC III",L9=FALSE,"IC IV",M9=TRUE,"EC I",N9=TRUE,"EC II",O9=TRUE,"EC III",R9>0,"EC IV",Q9=TRUE,"EC V",S9<>"","SA"),"OK") -> IC III | V9: SA | W9: Sem acesso | X9: =COUNTIFS(T:T,V9) -> 2 | Y9: =COUNTIFS($T:$T,$V9,$G:$G,Y$1) -> 0 | Z9: =COUNTIFS($T:$T,$V9,$G:$G,Z$1) -> 2 | AB9: =AB8-X9 -> 24 | AC9: =AC8-Y9 -> 3 | AD9: =AD8-Z9 -> 21
A10: =A9+1 -> 9 | B10: A detailed review on word embedding techniques with emphasis onword2vec | C10: https://link.springer.com/article/10.1007/s11042-023-17007-z | D10: 2024 | E10: 176 | F10: nan | G10: Google Scholar | H10: ['Dense Embeddings'] | I10: =LEN(H10)-LEN(SUBSTITUTE(H10,",",""))+1 -> 1 | J10: TRUE | K10: TRUE | L10: FALSE | M10: FALSE | N10: FALSE | O10: FALSE | T10: =IFERROR(IFS(K10=FALSE,"IC III",L10=FALSE,"IC IV",M10=TRUE,"EC I",N10=TRUE,"EC II",O10=TRUE,"EC III",R10>0,"EC IV",Q10=TRUE,"EC V",S10<>"","SA"),"OK") -> IC IV | V10: OK | W10: Ler Completo | X10: =COUNTIFS(T:T,V10) -> 24 | Y10: =COUNTIFS($T:$T,$V10,$G:$G,Y$1) -> 3 | Z10: =COUNTIFS($T:$T,$V10,$G:$G,Z$1) -> 21 | AB10: =AB9-X10 -> 0 | AC10: =AC9-Y10 -> 0 | AD10: =AD9-Z10 -> 0
A11: =A10+1 -> 10 | B11: A graph neural network-based machine learning model for sentiment polarity and behavior identification of COVID patients | C11: https://link.springer.com/article/10.1007/s41060-023-00469-7 | D11: 2023 | E11: -1 | F11: None | G11: Springer International Journal of Data Science and Analytics | H11: ['Literature Reviews', 'Applied cases'] | I11: =LEN(H11)-LEN(SUBSTITUTE(H11,",",""))+1 -> 2 | J11: TRUE | K11: TRUE | L11: TRUE | M11: FALSE | N11: FALSE | O11: FALSE | P11: TRUE | Q11: TRUE | T11: =IFERROR(IFS(K11=FALSE,"IC III",L11=FALSE,"IC IV",M11=TRUE,"EC I",N11=TRUE,"EC II",O11=TRUE,"EC III",R11>0,"EC IV",Q11=TRUE,"EC V",S11<>"","SA"),"OK") -> EC V
A12: =A11+1 -> 11 | B12: A hybrid deep learning neural network for early plant disease diagnosis using a real-world Wheat–Barley vision dataset: challenges and solutions | C12: https://link.springer.com/article/10.1007/s41060-024-00578-x | D12: 2024 | E12: -1 | F12: None | G12: Springer International Journal of Data Science and Analytics | H12: ['Comparison of methods'] | I12: =LEN(H12)-LEN(SUBSTITUTE(H12,",",""))+1 -> 1 | J12: TRUE | K12: TRUE | L12: TRUE | M12: FALSE | N12: FALSE | O12: FALSE | P12: TRUE | Q12: TRUE | T12: =IFERROR(IFS(K12=FALSE,"IC III",L12=FALSE,"IC IV",M12=TRUE,"EC I",N12=TRUE,"EC II",O12=TRUE,"EC III",R12>0,"EC IV",Q12=TRUE,"EC V",S12<>"","SA"),"OK") -> EC V | V12: Duplicados
A13: =A12+1 -> 12 | B13: A hybrid framework for fake news detection using transformer models with MASHAP | C13: https://link.springer.com/article/10.1007/s41060-025-00952-3 | D13: 2025 | E13: -1 | F13: None | G13: Springer International Journal of Data Science and Analytics | H13: ['Classic Methods', 'Dense Embeddings', 'Comparison of methods'] | I13: =LEN(H13)-LEN(SUBSTITUTE(H13,",",""))+1 -> 3 | J13: TRUE | K13: TRUE | L13: FALSE | M13: TRUE | N13: FALSE | O13: FALSE | T13: =IFERROR(IFS(K13=FALSE,"IC III",L13=FALSE,"IC IV",M13=TRUE,"EC I",N13=TRUE,"EC II",O13=TRUE,"EC III",R13>0,"EC IV",Q13=TRUE,"EC V",S13<>"","SA"),"OK") -> IC IV | V13: EC V | X13: =SUMIFS(I:I,T:T,V8)-X8 -> 3 | Y13: =SUMIFS($I:$I,$T:$T,$V8,$G:$G,Y$1)-Y8 -> 3 | Z13: =SUMIFS($I:$I,$T:$T,$V8,$G:$G,Z$1)-Z8 -> 0
A14: =A13+1 -> 13 | B14: A hybrid self attentive linearized phrase structured transformer based RNN for financial sentence analysis with sentence level explainability | C14: https://www.nature.com/articles/s41598-025-09265-8 | D14: 2025 | E14: 7 | F14: https://www.nature.com/articles/s41598-025-09265-8.pdf | G14: Google Scholar | H14: ['Applied cases'] | I14: =LEN(H14)-LEN(SUBSTITUTE(H14,",",""))+1 -> 1 | J14: TRUE | K14: TRUE | L14: TRUE | M14: FALSE | N14: FALSE | O14: FALSE | P14: TRUE | Q14: TRUE | T14: =IFERROR(IFS(K14=FALSE,"IC III",L14=FALSE,"IC IV",M14=TRUE,"EC I",N14=TRUE,"EC II",O14=TRUE,"EC III",R14>0,"EC IV",Q14=TRUE,"EC V",S14<>"","SA"),"OK") -> EC V | V14: SA | X14: =SUMIFS(I:I,T:T,V9)-X9 -> 1 | Y14: =SUMIFS($I:$I,$T:$T,$V9,$G:$G,Y$1)-Y9 -> 0 | Z14: =SUMIFS($I:$I,$T:$T,$V9,$G:$G,Z$1)-Z9 -> 1
A15: =A14+1 -> 14 | B15: A late fusion framework using whale optimization technique and attention-BiLSTM for fake news detection | C15: https://link.springer.com/article/10.1007/s41060-024-00515-y | D15: 2024 | E15: -1 | F15: None | G15: Springer International Journal of Data Science and Analytics | H15: ['Classic Methods', 'Dense Embeddings', 'Comparison of methods', 'Applied cases'] | I15: =LEN(H15)-LEN(SUBSTITUTE(H15,",",""))+1 -> 4 | J15: TRUE | K15: TRUE | L15: FALSE | M15: TRUE | N15: FALSE | O15: FALSE | T15: =IFERROR(IFS(K15=FALSE,"IC III",L15=FALSE,"IC IV",M15=TRUE,"EC I",N15=TRUE,"EC II",O15=TRUE,"EC III",R15>0,"EC IV",Q15=TRUE,"EC V",S15<>"","SA"),"OK") -> IC IV | V15: OK | X15: =SUMIFS(I:I,T:T,V10)-X10 -> 2 | Y15: =SUMIFS($I:$I,$T:$T,$V10,$G:$G,Y$1)-Y10 -> 2 | Z15: =SUMIFS($I:$I,$T:$T,$V10,$G:$G,Z$1)-Z10 -> 0
A16: =A15+1 -> 15 | B16: A layer-wise survey on internal modifications in BERT and its variants: techniques, applications, and performance trade-offs | C16: https://link.springer.com/article/10.1007/s41060-025-00986-7 | D16: 2025 | E16: -1 | F16: None | G16: Springer International Journal of Data Science and Analytics | H16: ['Dense Embeddings', 'Contextual Embeddings', 'Literature Reviews', 'Applied cases'] | I16: =LEN(H16)-LEN(SUBSTITUTE(H16,",",""))+1 -> 4 | J16: TRUE | K16: TRUE | L16: FALSE | M16: TRUE | N16: TRUE | O16: FALSE | T16: =IFERROR(IFS(K16=FALSE,"IC III",L16=FALSE,"IC IV",M16=TRUE,"EC I",N16=TRUE,"EC II",O16=TRUE,"EC III",R16>0,"EC IV",Q16=TRUE,"EC V",S16<>"","SA"),"OK") -> IC IV
A17: =A16+1 -> 16 | B17: A novel hybrid support vector machine with firebug swarm optimization | C17: https://link.springer.com/article/10.1007/s41060-024-00520-1 | D17: 2024 | E17: -1 | F17: None | G17: Springer International Journal of Data Science and Analytics | H17: ['Comparison of methods'] | I17: =LEN(H17)-LEN(SUBSTITUTE(H17,",",""))+1 -> 1 | J17: TRUE | K17: FALSE | L17: FALSE | M17: TRUE | N17: TRUE | O17: TRUE | T17: =IFERROR(IFS(K17=FALSE,"IC III",L17=FALSE,"IC IV",M17=TRUE,"EC I",N17=TRUE,"EC II",O17=TRUE,"EC III",R17>0,"EC IV",Q17=TRUE,"EC V",S17<>"","SA"),"OK") -> IC III
A18: =A17+1 -> 17 | B18: Dual layer Cogni-insight deep-mood encoder: a two-tiered approach for depression detection | C18: https://ieeexplore.ieee.org/abstract/document/10516113/ | D18: 2024 | E18: 1 | F18: nan | G18: Google Scholar | H18: ['Literature Reviews'] | I18: =LEN(H18)-LEN(SUBSTITUTE(H18,",",""))+1 -> 1 | J18: TRUE | K18: TRUE | L18: TRUE | M18: FALSE | N18: FALSE | O18: FALSE | P18: TRUE | Q18: TRUE | T18: =IFERROR(IFS(K18=FALSE,"IC III",L18=FALSE,"IC IV",M18=TRUE,"EC I",N18=TRUE,"EC II",O18=TRUE,"EC III",R18>0,"EC IV",Q18=TRUE,"EC V",S18<>"","SA"),"OK") -> EC V
A19: =A18+1 -> 18 | B19: A review of sentiment analysis: tasks, applications, and deep learning techniques | C19: https://link.springer.com/article/10.1007/s41060-024-00594-x | D19: 2024 | E19: -1 | F19: None | G19: Springer International Journal of Data Science and Analytics | H19: ['Classic Methods', 'Dense Embeddings', 'Literature Reviews', 'Applied cases'] | I19: =LEN(H19)-LEN(SUBSTITUTE(H19,",",""))+1 -> 4 | J19: TRUE | K19: TRUE | L19: FALSE | M19: TRUE | N19: FALSE | O19: FALSE | T19: =IFERROR(IFS(K19=FALSE,"IC III",L19=FALSE,"IC IV",M19=TRUE,"EC I",N19=TRUE,"EC II",O19=TRUE,"EC III",R19>0,"EC IV",Q19=TRUE,"EC V",S19<>"","SA"),"OK") -> IC IV
A20: =A19+1 -> 19 | B20: A review of web infodemic analysis and detection trends across multi-modalities using deep neural network | C20: https://link.springer.com/article/10.1007/s41060-025-00727-w | D20: 2025 | E20: -1 | F20: None | G20: Springer International Journal of Data Science and Analytics | H20: ['Classic Methods', 'Dense Embeddings', 'Comparison of methods', 'Literature Reviews', 'Applied cases'] | I20: =LEN(H20)-LEN(SUBSTITUTE(H20,",",""))+1 -> 5 | J20: TRUE | K20: TRUE | L20: FALSE | M20: TRUE | N20: FALSE | O20: FALSE | T20: =IFERROR(IFS(K20=FALSE,"IC III",L20=FALSE,"IC IV",M20=TRUE,"EC I",N20=TRUE,"EC II",O20=TRUE,"EC III",R20>0,"EC IV",Q20=TRUE,"EC V",S20<>"","SA"),"OK") -> IC IV
A21: =A20+1 -> 20 | B21: A selective model for transfer learning in CNNs: optimization of fine-tuning layers | C21: https://link.springer.com/article/10.1007/s41060-024-00697-5 | D21: 2024 | E21: -1 | F21: None | G21: Springer International Journal of Data Science and Analytics | H21: ['Applied cases'] | I21: =LEN(H21)-LEN(SUBSTITUTE(H21,",",""))+1 -> 1 | J21: TRUE | K21: FALSE | L21: FALSE | M21: TRUE | N21: TRUE | O21: TRUE | T21: =IFERROR(IFS(K21=FALSE,"IC III",L21=FALSE,"IC IV",M21=TRUE,"EC I",N21=TRUE,"EC II",O21=TRUE,"EC III",R21>0,"EC IV",Q21=TRUE,"EC V",S21<>"","SA"),"OK") -> IC III
A22: =A21+1 -> 21 | B22: A similarity-based oversampling method for multi-label imbalanced text data | C22: https://link.springer.com/article/10.1007/s41060-025-00966-x | D22: 2025 | E22: -1 | F22: None | G22: Springer International Journal of Data Science and Analytics | H22: ['Dense Embeddings', 'Literature Reviews'] | I22: =LEN(H22)-LEN(SUBSTITUTE(H22,",",""))+1 -> 2 | J22: TRUE | K22: TRUE | L22: FALSE | M22: TRUE | N22: FALSE | O22: FALSE | T22: =IFERROR(IFS(K22=FALSE,"IC III",L22=FALSE,"IC IV",M22=TRUE,"EC I",N22=TRUE,"EC II",O22=TRUE,"EC III",R22>0,"EC IV",Q22=TRUE,"EC V",S22<>"","SA"),"OK") -> IC IV
A23: =A22+1 -> 22 | B23: A survey of approximate big data computing with the random sample partition (RSP) | C23: https://link.springer.com/article/10.1007/s41060-025-00916-7 | D23: 2025 | E23: -1 | F23: None | G23: Springer International Journal of Data Science and Analytics | H23: ['Applied cases'] | I23: =LEN(H23)-LEN(SUBSTITUTE(H23,",",""))+1 -> 1 | J23: TRUE | K23: FALSE | L23: FALSE | M23: TRUE | N23: TRUE | O23: TRUE | T23: =IFERROR(IFS(K23=FALSE,"IC III",L23=FALSE,"IC IV",M23=TRUE,"EC I",N23=TRUE,"EC II",O23=TRUE,"EC III",R23>0,"EC IV",Q23=TRUE,"EC V",S23<>"","SA"),"OK") -> IC III
A24: =A23+1 -> 23 | B24: A survey of sentiment analysis methods based on graph neural network | C24: https://link.springer.com/article/10.1007/s41060-025-00714-1 | D24: 2025 | E24: -1 | F24: None | G24: Springer International Journal of Data Science and Analytics | H24: ['Classic Methods', 'Dense Embeddings', 'Comparison of methods', 'Literature Reviews', 'Applied cases'] | I24: =LEN(H24)-LEN(SUBSTITUTE(H24,",",""))+1 -> 5 | J24: TRUE | K24: TRUE | L24: FALSE | M24: TRUE | N24: FALSE | O24: FALSE | T24: =IFERROR(IFS(K24=FALSE,"IC III",L24=FALSE,"IC IV",M24=TRUE,"EC I",N24=TRUE,"EC II",O24=TRUE,"EC III",R24>0,"EC IV",Q24=TRUE,"EC V",S24<>"","SA"),"OK") -> IC IV
A25: =A24+1 -> 24 | B25: A survey oftext representationand embedding techniques in nlp | C25: https://ieeexplore.ieee.org/abstract/document/10098736/ | D25: 2023 | E25: 267 | F25: https://ieeexplore.ieee.org/iel7/6287639/6514899/10098736.pdf | G25: Google Scholar | H25: ['Classic Methods', 'Comparison of methods'] | I25: =LEN(H25)-LEN(SUBSTITUTE(H25,",",""))+1 -> 2 | J25: TRUE | K25: TRUE | L25: FALSE | M25: TRUE | N25: FALSE | O25: FALSE | T25: =IFERROR(IFS(K25=FALSE,"IC III",L25=FALSE,"IC IV",M25=TRUE,"EC I",N25=TRUE,"EC II",O25=TRUE,"EC III",R25>0,"EC IV",Q25=TRUE,"EC V",S25<>"","SA"),"OK") -> IC IV
A26: =A25+1 -> 25 | B26: A systematic review of machine learning approaches for detecting deceptive activities on social media: methods, challenges, and biases | C26: https://link.springer.com/article/10.1007/s41060-025-00850-8 | D26: 2025 | E26: -1 | F26: None | G26: Springer International Journal of Data Science and Analytics | H26: ['Classic Methods', 'Dense Embeddings', 'Applied cases'] | I26: =LEN(H26)-LEN(SUBSTITUTE(H26,",",""))+1 -> 3 | J26: TRUE | K26: TRUE | L26: FALSE | M26: TRUE | N26: FALSE | O26: FALSE | T26: =IFERROR(IFS(K26=FALSE,"IC III",L26=FALSE,"IC IV",M26=TRUE,"EC I",N26=TRUE,"EC II",O26=TRUE,"EC III",R26>0,"EC IV",Q26=TRUE,"EC V",S26<>"","SA"),"OK") -> IC IV
A27: =A26+1 -> 26 | B27: AI and data science for smart emergency, crisis and disaster resilience | C27: https://link.springer.com/article/10.1007/s41060-023-00393-w | D27: 2023 | E27: -1 | F27: None | G27: Springer International Journal of Data Science and Analytics | H27: ['Applied cases'] | I27: =LEN(H27)-LEN(SUBSTITUTE(H27,",",""))+1 -> 1 | J27: TRUE | K27: TRUE | L27: FALSE | M27: FALSE | N27: FALSE | O27: TRUE | T27: =IFERROR(IFS(K27=FALSE,"IC III",L27=FALSE,"IC IV",M27=TRUE,"EC I",N27=TRUE,"EC II",O27=TRUE,"EC III",R27>0,"EC IV",Q27=TRUE,"EC V",S27<>"","SA"),"OK") -> IC IV
A28: =A27+1 -> 27 | B28: Acoustic andtext featuresanalysis for adult ADHD screening: A data-driven approach utilizing DIVA interview | C28: https://ieeexplore.ieee.org/abstract/document/10445184/ | D28: 2024 | E28: 22 | F28: https://ieeexplore.ieee.org/iel7/6221039/6563131/10445184.pdf | G28: Google Scholar | H28: ['Comparison of methods'] | I28: =LEN(H28)-LEN(SUBSTITUTE(H28,",",""))+1 -> 1 | J28: TRUE | K28: TRUE | L28: TRUE | M28: FALSE | N28: FALSE | O28: FALSE | P28: TRUE | Q28: TRUE | T28: =IFERROR(IFS(K28=FALSE,"IC III",L28=FALSE,"IC IV",M28=TRUE,"EC I",N28=TRUE,"EC II",O28=TRUE,"EC III",R28>0,"EC IV",Q28=TRUE,"EC V",S28<>"","SA"),"OK") -> EC V
A29: =A28+1 -> 28 | B29: Actuarial applications of natural language processing using transformers: Case studies for usingtext featuresin an actuarial context | C29: https://www.cambridge.org/core/journals/british-actuarial-journal/article/actuarial-applications-of-natural-language-processing-using-transformers-case-studies-for-using-text-features-in-an-actuarial-context/FE5758599524A5C5A837BE54A34155C5 | D29: 2024 | E29: 23 | F29: https://www.cambridge.org/core/services/aop-cambridge-core/content/view/FE5758599524A5C5A837BE54A34155C5/S1357321724000023a.pdf/actuarial_applications_of_natural_language_processing_using_transformers_case_studies_for_using_text_features_in_an_actuarial_context.pdf | G29: Google Scholar | H29: ['Dense Embeddings'] | I29: =LEN(H29)-LEN(SUBSTITUTE(H29,",",""))+1 -> 1 | J29: TRUE | K29: TRUE | L29: TRUE | M29: FALSE | N29: FALSE | O29: FALSE | P29: TRUE | Q29: TRUE | T29: =IFERROR(IFS(K29=FALSE,"IC III",L29=FALSE,"IC IV",M29=TRUE,"EC I",N29=TRUE,"EC II",O29=TRUE,"EC III",R29>0,"EC IV",Q29=TRUE,"EC V",S29<>"","SA"),"OK") -> EC V
A30: =A29+1 -> 29 | B30: Adequate Prompting Improves Performance of Regression Models of Emotional Content | C30: https://dl.acm.org/doi/abs/10.1145/3677525.3678653 | D30: 2024 | E30: 1 | F30: https://dl.acm.org/doi/pdf/10.1145/3677525.3678653 | G30: Google Scholar | H30: ['General'] | I30: =LEN(H30)-LEN(SUBSTITUTE(H30,",",""))+1 -> 1 | J30: TRUE | K30: TRUE | L30: TRUE | M30: FALSE | N30: FALSE | O30: FALSE | P30: TRUE | Q30: FALSE | T30: =IFERROR(IFS(K30=FALSE,"IC III",L30=FALSE,"IC IV",M30=TRUE,"EC I",N30=TRUE,"EC II",O30=TRUE,"EC III",R30>0,"EC IV",Q30=TRUE,"EC V",S30<>"","SA"),"OK") -> OK
A31: =A30+1 -> 30 | B31: Advancements in Large-Scale Image andText RepresentationLearning: A ComprehensiveReviewand Outlook | C31: https://ieeexplore.ieee.org/abstract/document/10883956/ | D31: 2025 | E31: 3 | F31: https://ieeexplore.ieee.org/iel8/6287639/6514899/10883956.pdf | G31: Google Scholar | H31: ['Literature Reviews'] | I31: =LEN(H31)-LEN(SUBSTITUTE(H31,",",""))+1 -> 1 | J31: TRUE | K31: TRUE | L31: FALSE | M31: TRUE | N31: FALSE | O31: FALSE | T31: =IFERROR(IFS(K31=FALSE,"IC III",L31=FALSE,"IC IV",M31=TRUE,"EC I",N31=TRUE,"EC II",O31=TRUE,"EC III",R31>0,"EC IV",Q31=TRUE,"EC V",S31<>"","SA"),"OK") -> IC IV
A32: =A31+1 -> 31 | B32: Advancements in feature selection and extraction methods for text mining: a review | C32: https://link.springer.com/article/10.1007/s42452-025-07587-w | D32: 2025 | E32: 2 | F32: https://link.springer.com/content/pdf/10.1007/s42452-025-07587-w.pdf | G32: Google Scholar | H32: ['Dense Embeddings'] | I32: =LEN(H32)-LEN(SUBSTITUTE(H32,",",""))+1 -> 1 | J32: TRUE | K32: TRUE | L32: FALSE | M32: TRUE | N32: TRUE | O32: FALSE | T32: =IFERROR(IFS(K32=FALSE,"IC III",L32=FALSE,"IC IV",M32=TRUE,"EC I",N32=TRUE,"EC II",O32=TRUE,"EC III",R32>0,"EC IV",Q32=TRUE,"EC V",S32<>"","SA"),"OK") -> IC IV
A33: =A32+1 -> 32 | B33: Empirical assessment of transformer-based neural network architecture in forecasting pollution trends | C33: https://link.springer.com/article/10.1007/s41060-023-00421-9 | D33: 2023 | E33: -1 | F33: None | G33: Springer International Journal of Data Science and Analytics | H33: ['Applied cases'] | I33: =LEN(H33)-LEN(SUBSTITUTE(H33,",",""))+1 -> 1 | J33: TRUE | K33: FALSE | L33: FALSE | M33: FALSE | N33: TRUE | O33: FALSE | P33: TRUE | Q33: FALSE | T33: =IFERROR(IFS(K33=FALSE,"IC III",L33=FALSE,"IC IV",M33=TRUE,"EC I",N33=TRUE,"EC II",O33=TRUE,"EC III",R33>0,"EC IV",Q33=TRUE,"EC V",S33<>"","SA"),"OK") -> IC III
A34: =A33+1 -> 33 | B34: An accurate spam email detection mechanism using XLNet | C34: https://link.springer.com/article/10.1007/s41060-025-00887-9 | D34: 2025 | E34: -1 | F34: None | G34: Springer International Journal of Data Science and Analytics | H34: ['Dense Embeddings', 'Literature Reviews'] | I34: =LEN(H34)-LEN(SUBSTITUTE(H34,",",""))+1 -> 2 | J34: TRUE | K34: FALSE | L34: FALSE | M34: TRUE | N34: FALSE | O34: FALSE | T34: =IFERROR(IFS(K34=FALSE,"IC III",L34=FALSE,"IC IV",M34=TRUE,"EC I",N34=TRUE,"EC II",O34=TRUE,"EC III",R34>0,"EC IV",Q34=TRUE,"EC V",S34<>"","SA"),"OK") -> IC III
A35: =A34+1 -> 34 | B35: An approach for web content classification withFastText | C35: https://link.springer.com/chapter/10.1007/978-981-97-0669-3_14 | D35: 2023 | E35: 5 | F35: nan | G35: Google Scholar | H35: ['Dense Embeddings'] | I35: =LEN(H35)-LEN(SUBSTITUTE(H35,",",""))+1 -> 1 | J35: TRUE | K35: TRUE | L35: FALSE | M35: TRUE | N35: FALSE | O35: FALSE | T35: =IFERROR(IFS(K35=FALSE,"IC III",L35=FALSE,"IC IV",M35=TRUE,"EC I",N35=TRUE,"EC II",O35=TRUE,"EC III",R35>0,"EC IV",Q35=TRUE,"EC V",S35<>"","SA"),"OK") -> IC IV
A36: =A35+1 -> 35 | B36: An extended survey concerning the significance of artificial intelligence and machine learning techniques for bug triage and management | C36: https://ieeexplore.ieee.org/abstract/document/10305170/ | D36: 2023 | E36: 17 | F36: https://ieeexplore.ieee.org/iel7/6287639/6514899/10305170.pdf | G36: Google Scholar | H36: ['General'] | I36: =LEN(H36)-LEN(SUBSTITUTE(H36,",",""))+1 -> 1 | J36: TRUE | K36: FALSE | L36: FALSE | M36: TRUE | N36: FALSE | O36: TRUE | T36: =IFERROR(IFS(K36=FALSE,"IC III",L36=FALSE,"IC IV",M36=TRUE,"EC I",N36=TRUE,"EC II",O36=TRUE,"EC III",R36>0,"EC IV",Q36=TRUE,"EC V",S36<>"","SA"),"OK") -> IC III
A37: =A36+1 -> 36 | B37: An innovative method for accurate NBA player performance forecasting and line-up optimization in daily fantasy sports | C37: https://link.springer.com/article/10.1007/s41060-024-00523-y | D37: 2024 | E37: -1 | F37: None | G37: Springer International Journal of Data Science and Analytics | H37: ['Applied cases'] | I37: =LEN(H37)-LEN(SUBSTITUTE(H37,",",""))+1 -> 1 | J37: TRUE | K37: FALSE | L37: FALSE | M37: FALSE | N37: TRUE | O37: FALSE | T37: =IFERROR(IFS(K37=FALSE,"IC III",L37=FALSE,"IC IV",M37=TRUE,"EC I",N37=TRUE,"EC II",O37=TRUE,"EC III",R37>0,"EC IV",Q37=TRUE,"EC V",S37<>"","SA"),"OK") -> IC III
A38: =A37+1 -> 37 | B38: An overview of methods and techniques in multimodal data fusion with application to healthcare | C38: https://link.springer.com/article/10.1007/s41060-025-00715-0 | D38: 2025 | E38: -1 | F38: None | G38: Springer International Journal of Data Science and Analytics | H38: ['Literature Reviews'] | I38: =LEN(H38)-LEN(SUBSTITUTE(H38,",",""))+1 -> 1 | J38: TRUE | K38: FALSE | L38: FALSE | M38: FALSE | N38: TRUE | O38: FALSE | T38: =IFERROR(IFS(K38=FALSE,"IC III",L38=FALSE,"IC IV",M38=TRUE,"EC I",N38=TRUE,"EC II",O38=TRUE,"EC III",R38>0,"EC IV",Q38=TRUE,"EC V",S38<>"","SA"),"OK") -> IC III
A39: =A38+1 -> 38 | B39: An overview of sentence ordering task | C39: https://link.springer.com/article/10.1007/s41060-024-00550-9 | D39: 2024 | E39: -1 | F39: None | G39: Springer International Journal of Data Science and Analytics | H39: ['Literature Reviews'] | I39: =LEN(H39)-LEN(SUBSTITUTE(H39,",",""))+1 -> 1 | J39: TRUE | K39: TRUE | L39: FALSE | M39: TRUE | N39: FALSE | O39: FALSE | T39: =IFERROR(IFS(K39=FALSE,"IC III",L39=FALSE,"IC IV",M39=TRUE,"EC I",N39=TRUE,"EC II",O39=TRUE,"EC III",R39>0,"EC IV",Q39=TRUE,"EC V",S39<>"","SA"),"OK") -> IC IV
A40: =A39+1 -> 39 | B40: Analysis of the Arab singer Shadia’s lyrics | C40: https://link.springer.com/article/10.1007/s41060-024-00669-9 | D40: 2024 | E40: -1 | F40: None | G40: Springer International Journal of Data Science and Analytics | H40: ['Classic Methods', 'Dense Embeddings', 'Applied cases'] | I40: =LEN(H40)-LEN(SUBSTITUTE(H40,",",""))+1 -> 3 | J40: TRUE | K40: TRUE | L40: FALSE | M40: TRUE | N40: FALSE | O40: FALSE | T40: =IFERROR(IFS(K40=FALSE,"IC III",L40=FALSE,"IC IV",M40=TRUE,"EC I",N40=TRUE,"EC II",O40=TRUE,"EC III",R40>0,"EC IV",Q40=TRUE,"EC V",S40<>"","SA"),"OK") -> IC IV
A41: =A40+1 -> 40 | B41: Artificial intelligence trend analysis in German business and politics: a web mining approach | C41: https://link.springer.com/article/10.1007/s41060-023-00483-9 | D41: 2023 | E41: -1 | F41: None | G41: Springer International Journal of Data Science and Analytics | H41: ['Dense Embeddings', 'Literature Reviews', 'Applied cases'] | I41: =LEN(H41)-LEN(SUBSTITUTE(H41,",",""))+1 -> 3 | J41: TRUE | K41: TRUE | L41: FALSE | M41: TRUE | N41: FALSE | O41: FALSE | T41: =IFERROR(IFS(K41=FALSE,"IC III",L41=FALSE,"IC IV",M41=TRUE,"EC I",N41=TRUE,"EC II",O41=TRUE,"EC III",R41>0,"EC IV",Q41=TRUE,"EC V",S41<>"","SA"),"OK") -> IC IV
A42: =A41+1 -> 41 | B42: Asif: Coupled data turns unimodal models to multimodal without training | C42: https://proceedings.neurips.cc/paper_files/paper/2023/hash/3186591903d9db31770ad131adb5ceb4-Abstract-Conference.html | D42: 2023 | E42: 56 | F42: https://proceedings.neurips.cc/paper_files/paper/2023/file/3186591903d9db31770ad131adb5ceb4-Paper-Conference.pdf | G42: Google Scholar | H42: ['Contextual Embeddings'] | I42: =LEN(H42)-LEN(SUBSTITUTE(H42,",",""))+1 -> 1 | J42: TRUE | K42: TRUE | L42: FALSE | M42: TRUE | N42: FALSE | O42: FALSE | T42: =IFERROR(IFS(K42=FALSE,"IC III",L42=FALSE,"IC IV",M42=TRUE,"EC I",N42=TRUE,"EC II",O42=TRUE,"EC III",R42>0,"EC IV",Q42=TRUE,"EC V",S42<>"","SA"),"OK") -> IC IV
A43: =A42+1 -> 42 | B43: Aspect-level multimodal sentiment analysis based on co-attention fusion | C43: https://link.springer.com/article/10.1007/s41060-023-00497-3 | D43: 2024 | E43: -1 | F43: None | G43: Springer International Journal of Data Science and Analytics | H43: ['Dense Embeddings', 'Comparison of methods', 'Applied cases'] | I43: =LEN(H43)-LEN(SUBSTITUTE(H43,",",""))+1 -> 3 | J43: TRUE | K43: TRUE | L43: TRUE | M43: FALSE | N43: FALSE | O43: FALSE | P43: TRUE | Q43: TRUE | T43: =IFERROR(IFS(K43=FALSE,"IC III",L43=FALSE,"IC IV",M43=TRUE,"EC I",N43=TRUE,"EC II",O43=TRUE,"EC III",R43>0,"EC IV",Q43=TRUE,"EC V",S43<>"","SA"),"OK") -> EC V
A44: =A43+1 -> 43 | B44: Asurveyoftext representationand embedding techniques in nlp | C44: https://ieeexplore.ieee.org/abstract/document/10098736/ | D44: 2023 | E44: 267 | F44: https://ieeexplore.ieee.org/iel7/6287639/6514899/10098736.pdf | G44: Google Scholar | H44: ['Literature Reviews'] | I44: =LEN(H44)-LEN(SUBSTITUTE(H44,",",""))+1 -> 1 | J44: TRUE | K44: TRUE | L44: FALSE | M44: TRUE | N44: FALSE | O44: FALSE | R44: 24 | T44: =IFERROR(IFS(K44=FALSE,"IC III",L44=FALSE,"IC IV",M44=TRUE,"EC I",N44=TRUE,"EC II",O44=TRUE,"EC III",R44>0,"EC IV",Q44=TRUE,"EC V",S44<>"","SA"),"OK") -> IC IV
A45: =A44+1 -> 44 | B45: Attention and meta-heuristic based general self-efficacy prediction model from multimodal social media dataset | C45: https://ieeexplore.ieee.org/abstract/document/10459187/ | D45: 2024 | E45: 11 | F45: https://ieeexplore.ieee.org/iel7/6287639/6514899/10459187.pdf | G45: Google Scholar | H45: ['Literature Reviews'] | I45: =LEN(H45)-LEN(SUBSTITUTE(H45,",",""))+1 -> 1 | J45: TRUE | K45: TRUE | L45: FALSE | M45: TRUE | N45: FALSE | O45: FALSE | T45: =IFERROR(IFS(K45=FALSE,"IC III",L45=FALSE,"IC IV",M45=TRUE,"EC I",N45=TRUE,"EC II",O45=TRUE,"EC III",R45>0,"EC IV",Q45=TRUE,"EC V",S45<>"","SA"),"OK") -> IC IV
A46: =A45+1 -> 45 | B46: Attention versus contrastive learning of tabular data: a data-centric benchmarking | C46: https://link.springer.com/article/10.1007/s41060-024-00681-z | D46: 2024 | E46: -1 | F46: None | G46: Springer International Journal of Data Science and Analytics | H46: ['Dense Embeddings'] | I46: =LEN(H46)-LEN(SUBSTITUTE(H46,",",""))+1 -> 1 | J46: TRUE | K46: TRUE | L46: FALSE | M46: TRUE | N46: FALSE | O46: FALSE | T46: =IFERROR(IFS(K46=FALSE,"IC III",L46=FALSE,"IC IV",M46=TRUE,"EC I",N46=TRUE,"EC II",O46=TRUE,"EC III",R46>0,"EC IV",Q46=TRUE,"EC V",S46<>"","SA"),"OK") -> IC IV
A47: =A46+1 -> 46 | B47: Author identification of literary works based on text analysis and deep learning | C47: https://www.cell.com/heliyon/fulltext/S2405-8440(24)01495-6 | D47: 2024 | E47: 12 | F47: https://www.cell.com/heliyon/pdf/S2405-8440(24)01495-6.pdf | G47: Google Scholar | H47: ['Comparison of methods'] | I47: =LEN(H47)-LEN(SUBSTITUTE(H47,",",""))+1 -> 1 | J47: TRUE | K47: TRUE | L47: FALSE | M47: TRUE | N47: FALSE | O47: FALSE | T47: =IFERROR(IFS(K47=FALSE,"IC III",L47=FALSE,"IC IV",M47=TRUE,"EC I",N47=TRUE,"EC II",O47=TRUE,"EC III",R47>0,"EC IV",Q47=TRUE,"EC V",S47<>"","SA"),"OK") -> IC IV
A48: =A47+1 -> 47 | B48: Automatic user story generation: a comprehensive systematic literature review | C48: https://link.springer.com/article/10.1007/s41060-024-00567-0 | D48: 2024 | E48: -1 | F48: None | G48: Springer International Journal of Data Science and Analytics | H48: ['Literature Reviews', 'Applied cases'] | I48: =LEN(H48)-LEN(SUBSTITUTE(H48,",",""))+1 -> 2 | J48: TRUE | K48: FALSE | L48: FALSE | M48: TRUE | N48: FALSE | O48: TRUE | T48: =IFERROR(IFS(K48=FALSE,"IC III",L48=FALSE,"IC IV",M48=TRUE,"EC I",N48=TRUE,"EC II",O48=TRUE,"EC III",R48>0,"EC IV",Q48=TRUE,"EC V",S48<>"","SA"),"OK") -> IC III
A49: =A48+1 -> 48 | B49: Automating systematic literature reviews with natural language processing and text mining: A systematicliterature review | C49: https://link.springer.com/chapter/10.1007/978-981-99-3243-6_7 | D49: 2023 | E49: 40 | F49: https://arxiv.org/pdf/2211.15397 | G49: Google Scholar | H49: ['Literature Reviews'] | I49: =LEN(H49)-LEN(SUBSTITUTE(H49,",",""))+1 -> 1 | J49: TRUE | K49: FALSE | L49: FALSE | M49: TRUE | N49: FALSE | O49: FALSE | T49: =IFERROR(IFS(K49=FALSE,"IC III",L49=FALSE,"IC IV",M49=TRUE,"EC I",N49=TRUE,"EC II",O49=TRUE,"EC III",R49>0,"EC IV",Q49=TRUE,"EC V",S49<>"","SA"),"OK") -> IC III
A50: =A49+1 -> 49 | B50: Comparative analysis of BERT andFastTextrepresentations on crowdfunding campaign success prediction | C50: https://peerj.com/articles/cs-2316/ | D50: 2024 | E50: 8 | F50: https://peerj.com/articles/cs-2316.pdf | G50: Google Scholar | H50: ['Dense Embeddings'] | I50: =LEN(H50)-LEN(SUBSTITUTE(H50,",",""))+1 -> 1 | J50: TRUE | K50: TRUE | L50: FALSE | M50: TRUE | N50: FALSE | O50: FALSE | T50: =IFERROR(IFS(K50=FALSE,"IC III",L50=FALSE,"IC IV",M50=TRUE,"EC I",N50=TRUE,"EC II",O50=TRUE,"EC III",R50>0,"EC IV",Q50=TRUE,"EC V",S50<>"","SA"),"OK") -> IC IV
A51: =A50+1 -> 50 | B51: Comparing Pre-Trained Embeddings and Domain-Independent Features forRegression-Based Evaluation of Task-Oriented Dialogue Systems | C51: https://aclanthology.org/2024.sigdial-1.52/ | D51: 2024 | E51: 2 | F51: https://aclanthology.org/2024.sigdial-1.52.pdf | G51: Google Scholar | H51: ['Contextual Embeddings'] | I51: =LEN(H51)-LEN(SUBSTITUTE(H51,",",""))+1 -> 1 | J51: TRUE | K51: TRUE | L51: TRUE | M51: FALSE | N51: FALSE | O51: FALSE | P51: TRUE | Q51: TRUE | T51: =IFERROR(IFS(K51=FALSE,"IC III",L51=FALSE,"IC IV",M51=TRUE,"EC I",N51=TRUE,"EC II",O51=TRUE,"EC III",R51>0,"EC IV",Q51=TRUE,"EC V",S51<>"","SA"),"OK") -> EC V
A52: =A51+1 -> 51 | B52: Conditional checkpoint selection strategy based on sentence structures for text to triple translation using BiLSTM encoder–decoder model | C52: https://link.springer.com/article/10.1007/s41060-024-00672-0 | D52: 2024 | E52: -1 | F52: None | G52: Springer International Journal of Data Science and Analytics | H52: ['Applied cases'] | I52: =LEN(H52)-LEN(SUBSTITUTE(H52,",",""))+1 -> 1 | J52: TRUE | K52: TRUE | L52: FALSE | M52: TRUE | N52: FALSE | O52: FALSE | T52: =IFERROR(IFS(K52=FALSE,"IC III",L52=FALSE,"IC IV",M52=TRUE,"EC I",N52=TRUE,"EC II",O52=TRUE,"EC III",R52>0,"EC IV",Q52=TRUE,"EC V",S52<>"","SA"),"OK") -> IC IV
A53: =A52+1 -> 52 | B53: Context-adaptive intelligent agents behaviors: multivariate LSTM-based decision making on the cryptocurrency market | C53: https://link.springer.com/article/10.1007/s41060-023-00435-3 | D53: 2023 | E53: -1 | F53: None | G53: Springer International Journal of Data Science and Analytics | H53: ['Applied cases'] | I53: =LEN(H53)-LEN(SUBSTITUTE(H53,",",""))+1 -> 1 | J53: TRUE | K53: FALSE | L53: FALSE | M53: FALSE | N53: TRUE | O53: FALSE | P53: TRUE | Q53: FALSE | T53: =IFERROR(IFS(K53=FALSE,"IC III",L53=FALSE,"IC IV",M53=TRUE,"EC I",N53=TRUE,"EC II",O53=TRUE,"EC III",R53>0,"EC IV",Q53=TRUE,"EC V",S53<>"","SA"),"OK") -> IC III
A54: =A53+1 -> 53 | B54: Contrastive text summarization: a survey | C54: https://link.springer.com/article/10.1007/s41060-023-00434-4 | D54: 2023 | E54: -1 | F54: None | G54: Springer International Journal of Data Science and Analytics | H54: ['Dense Embeddings'] | I54: =LEN(H54)-LEN(SUBSTITUTE(H54,",",""))+1 -> 1 | J54: TRUE | K54: FALSE | L54: FALSE | M54: FALSE | N54: FALSE | O54: TRUE | T54: =IFERROR(IFS(K54=FALSE,"IC III",L54=FALSE,"IC IV",M54=TRUE,"EC I",N54=TRUE,"EC II",O54=TRUE,"EC III",R54>0,"EC IV",Q54=TRUE,"EC V",S54<>"","SA"),"OK") -> IC III
A55: =A54+1 -> 54 | B55: Cyber insights: exploring the effectiveness of image-based and vector-based feature representations in insider threat detection | C55: https://link.springer.com/article/10.1007/s41060-025-00960-3 | D55: 2025 | E55: -1 | F55: None | G55: Springer International Journal of Data Science and Analytics | H55: ['Dense Embeddings', 'Literature Reviews'] | I55: =LEN(H55)-LEN(SUBSTITUTE(H55,",",""))+1 -> 2 | J55: TRUE | K55: TRUE | L55: FALSE | M55: TRUE | N55: FALSE | O55: FALSE | T55: =IFERROR(IFS(K55=FALSE,"IC III",L55=FALSE,"IC IV",M55=TRUE,"EC I",N55=TRUE,"EC II",O55=TRUE,"EC III",R55>0,"EC IV",Q55=TRUE,"EC V",S55<>"","SA"),"OK") -> IC IV
A56: =A55+1 -> 55 | B56: DarijaBERT: a step forward in NLP for the written Moroccan dialect | C56: https://link.springer.com/article/10.1007/s41060-023-00498-2 | D56: 2024 | E56: -1 | F56: None | G56: Springer International Journal of Data Science and Analytics | H56: ['Applied cases'] | I56: =LEN(H56)-LEN(SUBSTITUTE(H56,",",""))+1 -> 1 | J56: TRUE | K56: TRUE | L56: FALSE | M56: TRUE | N56: FALSE | O56: FALSE | T56: =IFERROR(IFS(K56=FALSE,"IC III",L56=FALSE,"IC IV",M56=TRUE,"EC I",N56=TRUE,"EC II",O56=TRUE,"EC III",R56>0,"EC IV",Q56=TRUE,"EC V",S56<>"","SA"),"OK") -> IC IV
A57: =A56+1 -> 56 | B57: Dating Greek papyri withtext regression | C57: https://aclanthology.org/2023.acl-long.556/ | D57: 2023 | E57: 8 | F57: https://aclanthology.org/2023.acl-long.556.pdf | G57: Google Scholar | H57: ['General'] | I57: =LEN(H57)-LEN(SUBSTITUTE(H57,",",""))+1 -> 1 | J57: TRUE | K57: TRUE | L57: TRUE | M57: FALSE | N57: FALSE | O57: FALSE | P57: TRUE | Q57: FALSE | T57: =IFERROR(IFS(K57=FALSE,"IC III",L57=FALSE,"IC IV",M57=TRUE,"EC I",N57=TRUE,"EC II",O57=TRUE,"EC III",R57>0,"EC IV",Q57=TRUE,"EC V",S57<>"","SA"),"OK") -> OK
A58: =A57+1 -> 57 | B58: Deciphering language disturbances in schizophrenia: A study using fine-tuned language models | C58: https://www.sciencedirect.com/science/article/pii/S0920996424003219 | D58: 2024 | E58: 7 | F58: nan | G58: Google Scholar | H58: ['Contextual Embeddings'] | I58: =LEN(H58)-LEN(SUBSTITUTE(H58,",",""))+1 -> 1 | J58: TRUE | K58: TRUE | L58: FALSE | M58: TRUE | N58: FALSE | O58: FALSE | T58: =IFERROR(IFS(K58=FALSE,"IC III",L58=FALSE,"IC IV",M58=TRUE,"EC I",N58=TRUE,"EC II",O58=TRUE,"EC III",R58>0,"EC IV",Q58=TRUE,"EC V",S58<>"","SA"),"OK") -> IC IV
A59: =A58+1 -> 58 | B59: Decoding reddit memes virality | C59: https://link.springer.com/article/10.1007/s41060-025-00772-5 | D59: 2025 | E59: -1 | F59: None | G59: Springer International Journal of Data Science and Analytics | H59: ['Comparison of methods', 'Applied cases'] | I59: =LEN(H59)-LEN(SUBSTITUTE(H59,",",""))+1 -> 2 | J59: TRUE | K59: TRUE | L59: FALSE | M59: TRUE | N59: FALSE | O59: FALSE | T59: =IFERROR(IFS(K59=FALSE,"IC III",L59=FALSE,"IC IV",M59=TRUE,"EC I",N59=TRUE,"EC II",O59=TRUE,"EC III",R59>0,"EC IV",Q59=TRUE,"EC V",S59<>"","SA"),"OK") -> IC IV
A60: =A59+1 -> 59 | B60: Deep learning and transfer learning to understand emotions: a PoliEMO dataset and multi-label classification in Indian elections | C60: https://link.springer.com/article/10.1007/s41060-025-00738-7 | D60: 2025 | E60: -1 | F60: None | G60: Springer International Journal of Data Science and Analytics | H60: ['Classic Methods', 'Dense Embeddings', 'Applied cases'] | I60: =LEN(H60)-LEN(SUBSTITUTE(H60,",",""))+1 -> 3 | J60: TRUE | K60: FALSE | L60: FALSE | M60: TRUE | N60: FALSE | O60: FALSE | T60: =IFERROR(IFS(K60=FALSE,"IC III",L60=FALSE,"IC IV",M60=TRUE,"EC I",N60=TRUE,"EC II",O60=TRUE,"EC III",R60>0,"EC IV",Q60=TRUE,"EC V",S60<>"","SA"),"OK") -> IC III
A61: =A60+1 -> 60 | B61: Deep learning for hate speech detection: a comparative study | C61: https://link.springer.com/article/10.1007/s41060-024-00650-6 | D61: 2024 | E61: -1 | F61: None | G61: Springer International Journal of Data Science and Analytics | H61: ['Dense Embeddings', 'Contextual Embeddings', 'Applied cases'] | I61: =LEN(H61)-LEN(SUBSTITUTE(H61,",",""))+1 -> 3 | J61: TRUE | K61: TRUE | L61: FALSE | M61: TRUE | N61: FALSE | O61: FALSE | T61: =IFERROR(IFS(K61=FALSE,"IC III",L61=FALSE,"IC IV",M61=TRUE,"EC I",N61=TRUE,"EC II",O61=TRUE,"EC III",R61>0,"EC IV",Q61=TRUE,"EC V",S61<>"","SA"),"OK") -> IC IV
A62: =A61+1 -> 61 | B62: Deep learning, graph-basedtext representationand classification: a survey, perspectives and challenges | C62: https://link.springer.com/article/10.1007/s10462-022-10265-7 | D62: 2023 | E62: 68 | F62: nan | G62: Google Scholar | H62: ['Classic Methods', 'Comparison of methods'] | I62: =LEN(H62)-LEN(SUBSTITUTE(H62,",",""))+1 -> 2 | J62: TRUE | K62: TRUE | L62: FALSE | M62: TRUE | N62: FALSE | O62: FALSE | T62: =IFERROR(IFS(K62=FALSE,"IC III",L62=FALSE,"IC IV",M62=TRUE,"EC I",N62=TRUE,"EC II",O62=TRUE,"EC III",R62>0,"EC IV",Q62=TRUE,"EC V",S62<>"","SA"),"OK") -> IC IV
A63: =A62+1 -> 62 | B63: Deep learning, graph-basedtext representationand classification: asurvey, perspectives and challenges | C63: https://link.springer.com/article/10.1007/s10462-022-10265-7 | D63: 2023 | E63: 68 | F63: nan | G63: Google Scholar | H63: ['Literature Reviews'] | I63: =LEN(H63)-LEN(SUBSTITUTE(H63,",",""))+1 -> 1 | J63: TRUE | K63: FALSE | L63: FALSE | M63: TRUE | N63: TRUE | O63: TRUE | R63: 61 | T63: =IFERROR(IFS(K63=FALSE,"IC III",L63=FALSE,"IC IV",M63=TRUE,"EC I",N63=TRUE,"EC II",O63=TRUE,"EC III",R63>0,"EC IV",Q63=TRUE,"EC V",S63<>"","SA"),"OK") -> IC III
A64: =A63+1 -> 63 | B64: Deep multi-task learning: a review of concepts, methods, and cross-domain applications | C64: https://link.springer.com/article/10.1007/s41060-025-00892-y | D64: 2025 | E64: -1 | F64: None | G64: Springer International Journal of Data Science and Analytics | H64: ['Dense Embeddings', 'Applied cases'] | I64: =LEN(H64)-LEN(SUBSTITUTE(H64,",",""))+1 -> 2 | J64: TRUE | K64: FALSE | L64: FALSE | M64: TRUE | N64: FALSE | O64: TRUE | T64: =IFERROR(IFS(K64=FALSE,"IC III",L64=FALSE,"IC IV",M64=TRUE,"EC I",N64=TRUE,"EC II",O64=TRUE,"EC III",R64>0,"EC IV",Q64=TRUE,"EC V",S64<>"","SA"),"OK") -> IC III
A65: =A64+1 -> 64 | B65: Deep reinforcement learning approach for ontology matching problem | C65: https://link.springer.com/article/10.1007/s41060-023-00425-5 | D65: 2023 | E65: -1 | F65: None | G65: Springer International Journal of Data Science and Analytics | H65: ['Dense Embeddings'] | I65: =LEN(H65)-LEN(SUBSTITUTE(H65,",",""))+1 -> 1 | J65: TRUE | K65: FALSE | L65: FALSE | M65: TRUE | N65: FALSE | O65: TRUE | T65: =IFERROR(IFS(K65=FALSE,"IC III",L65=FALSE,"IC IV",M65=TRUE,"EC I",N65=TRUE,"EC II",O65=TRUE,"EC III",R65>0,"EC IV",Q65=TRUE,"EC V",S65<>"","SA"),"OK") -> IC III
A66: =A65+1 -> 65 | B66: DeepBERT-XAI: a dual BERT approach with XAI for sentiment analysis of airline tweet data | C66: https://link.springer.com/article/10.1007/s41060-025-00967-w | D66: 2025 | E66: -1 | F66: None | G66: Springer International Journal of Data Science and Analytics | H66: ['Classic Methods', 'Applied cases'] | I66: =LEN(H66)-LEN(SUBSTITUTE(H66,",",""))+1 -> 2 | J66: TRUE | K66: TRUE | L66: FALSE | M66: TRUE | N66: FALSE | O66: FALSE | T66: =IFERROR(IFS(K66=FALSE,"IC III",L66=FALSE,"IC IV",M66=TRUE,"EC I",N66=TRUE,"EC II",O66=TRUE,"EC III",R66>0,"EC IV",Q66=TRUE,"EC V",S66<>"","SA"),"OK") -> IC IV
A67: =A66+1 -> 66 | B67: Depression Detection in Indonesian X Social Media Text using Convolutional Neural Networks and Long Short-Term Memory with TF-IDF andFastTextMethods | C67: https://jutif.if.unsoed.ac.id/index.php/jurnal/article/view/4206 | D67: 2025 | E67: 5 | F67: https://jutif.if.unsoed.ac.id/index.php/jurnal/article/download/4206/825 | G67: Google Scholar | H67: ['Dense Embeddings'] | I67: =LEN(H67)-LEN(SUBSTITUTE(H67,",",""))+1 -> 1 | J67: TRUE | K67: TRUE | L67: FALSE | M67: TRUE | N67: FALSE | O67: FALSE | T67: =IFERROR(IFS(K67=FALSE,"IC III",L67=FALSE,"IC IV",M67=TRUE,"EC I",N67=TRUE,"EC II",O67=TRUE,"EC III",R67>0,"EC IV",Q67=TRUE,"EC V",S67<>"","SA"),"OK") -> IC IV
A68: =A67+1 -> 67 | B68: Designing a forecasting assistant of the Bitcoin price based on deep learning using market sentiment analysis and multiple feature extraction | C68: https://link.springer.com/article/10.1007/s00500-023-09028-5 | D68: 2023 | E68: 17 | F68: https://www.researchsquare.com/article/rs-1341589/latest.pdf | G68: Google Scholar | H68: ['Literature Reviews'] | I68: =LEN(H68)-LEN(SUBSTITUTE(H68,",",""))+1 -> 1 | J68: TRUE | K68: TRUE | L68: TRUE | M68: FALSE | N68: FALSE | O68: FALSE | P68: TRUE | Q68: FALSE | T68: =IFERROR(IFS(K68=FALSE,"IC III",L68=FALSE,"IC IV",M68=TRUE,"EC I",N68=TRUE,"EC II",O68=TRUE,"EC III",R68>0,"EC IV",Q68=TRUE,"EC V",S68<>"","SA"),"OK") -> OK
A69: =A68+1 -> 68 | B69: Detection of homophobia and transphobia in YouTube comments | C69: https://link.springer.com/article/10.1007/s41060-023-00400-0 | D69: 2023 | E69: -1 | F69: None | G69: Springer International Journal of Data Science and Analytics | H69: ['Dense Embeddings', 'Contextual Embeddings'] | I69: =LEN(H69)-LEN(SUBSTITUTE(H69,",",""))+1 -> 2 | J69: TRUE | K69: TRUE | L69: FALSE | M69: TRUE | N69: FALSE | O69: FALSE | T69: =IFERROR(IFS(K69=FALSE,"IC III",L69=FALSE,"IC IV",M69=TRUE,"EC I",N69=TRUE,"EC II",O69=TRUE,"EC III",R69>0,"EC IV",Q69=TRUE,"EC V",S69<>"","SA"),"OK") -> IC IV
A70: =A69+1 -> 69 | B70: Don't Get Too Excited-Eliciting Emotions in LLMs | C70: https://dl.acm.org/doi/abs/10.1145/3706599.3720191 | D70: 2025 | E70: 3 | F70: https://dl.acm.org/doi/pdf/10.1145/3706599.3720191 | G70: Google Scholar | H70: ['General'] | I70: =LEN(H70)-LEN(SUBSTITUTE(H70,",",""))+1 -> 1 | J70: TRUE | K70: FALSE | L70: FALSE | M70: TRUE | N70: FALSE | O70: FALSE | T70: =IFERROR(IFS(K70=FALSE,"IC III",L70=FALSE,"IC IV",M70=TRUE,"EC I",N70=TRUE,"EC II",O70=TRUE,"EC III",R70>0,"EC IV",Q70=TRUE,"EC V",S70<>"","SA"),"OK") -> IC III
A71: =A70+1 -> 70 | B71: Investigation of graph-based clustering approaches along with graph neural networks for modeling armed conflict in Bangladesh | C71: https://link.springer.com/article/10.1007/s41060-024-00572-3 | D71: 2024 | E71: -1 | F71: None | G71: Springer International Journal of Data Science and Analytics | H71: ['Applied cases'] | I71: =LEN(H71)-LEN(SUBSTITUTE(H71,",",""))+1 -> 1 | J71: TRUE | K71: FALSE | L71: FALSE | M71: FALSE | N71: TRUE | O71: FALSE | P71: TRUE | Q71: FALSE | T71: =IFERROR(IFS(K71=FALSE,"IC III",L71=FALSE,"IC IV",M71=TRUE,"EC I",N71=TRUE,"EC II",O71=TRUE,"EC III",R71>0,"EC IV",Q71=TRUE,"EC V",S71<>"","SA"),"OK") -> IC III
A72: =A71+1 -> 71 | B72: Duo satellite-based remotely sensed land surface temperature prediction by various methods of machine learning | C72: https://link.springer.com/article/10.1007/s41060-023-00459-9 | D72: 2023 | E72: -1 | F72: None | G72: Springer International Journal of Data Science and Analytics | H72: ['Applied cases'] | I72: =LEN(H72)-LEN(SUBSTITUTE(H72,",",""))+1 -> 1 | J72: TRUE | K72: FALSE | L72: TRUE | M72: FALSE | N72: FALSE | O72: FALSE | T72: =IFERROR(IFS(K72=FALSE,"IC III",L72=FALSE,"IC IV",M72=TRUE,"EC I",N72=TRUE,"EC II",O72=TRUE,"EC III",R72>0,"EC IV",Q72=TRUE,"EC V",S72<>"","SA"),"OK") -> IC III
A73: =A72+1 -> 72 | B73: Efficient graph-based spectral techniques for data with few labeled samples | C73: https://link.springer.com/article/10.1007/s41060-023-00403-x | D73: 2023 | E73: -1 | F73: None | G73: Springer International Journal of Data Science and Analytics | H73: ['Classic Methods'] | I73: =LEN(H73)-LEN(SUBSTITUTE(H73,",",""))+1 -> 1 | J73: TRUE | K73: TRUE | L73: FALSE | M73: TRUE | N73: FALSE | O73: FALSE | T73: =IFERROR(IFS(K73=FALSE,"IC III",L73=FALSE,"IC IV",M73=TRUE,"EC I",N73=TRUE,"EC II",O73=TRUE,"EC III",R73>0,"EC IV",Q73=TRUE,"EC V",S73<>"","SA"),"OK") -> IC IV
A74: =A73+1 -> 73 | B74: Embeddingregression: Models for context-specific description and inference | C74: https://www.cambridge.org/core/journals/american-political-science-review/article/embedding-regression-models-for-contextspecific-description-and-inference/4C90013E5C714C8483ED95CC699022FB | D74: 2023 | E74: 121 | F74: https://www.cambridge.org/core/services/aop-cambridge-core/content/view/4C90013E5C714C8483ED95CC699022FB/S0003055422001228a.pdf/div-class-title-embedding-regression-models-for-context-specific-description-and-inference-div.pdf | G74: Google Scholar | H74: ['Dense Embeddings'] | I74: =LEN(H74)-LEN(SUBSTITUTE(H74,",",""))+1 -> 1 | J74: TRUE | K74: TRUE | L74: TRUE | M74: FALSE | N74: FALSE | O74: FALSE | P74: TRUE | Q74: FALSE | T74: =IFERROR(IFS(K74=FALSE,"IC III",L74=FALSE,"IC IV",M74=TRUE,"EC I",N74=TRUE,"EC II",O74=TRUE,"EC III",R74>0,"EC IV",Q74=TRUE,"EC V",S74<>"","SA"),"OK") -> OK
A75: =A74+1 -> 74 | B75: Predicting normalized difference vegetation index using a deep attention network with bidirectional GRU: a hybrid parametric optimization approach | C75: https://link.springer.com/article/10.1007/s41060-024-00640-8 | D75: 2024 | E75: -1 | F75: None | G75: Springer International Journal of Data Science and Analytics | H75: ['Comparison of methods', 'Literature Reviews'] | I75: =LEN(H75)-LEN(SUBSTITUTE(H75,",",""))+1 -> 2 | J75: TRUE | K75: FALSE | L75: FALSE | M75: FALSE | N75: TRUE | O75: FALSE | P75: TRUE | Q75: FALSE | T75: =IFERROR(IFS(K75=FALSE,"IC III",L75=FALSE,"IC IV",M75=TRUE,"EC I",N75=TRUE,"EC II",O75=TRUE,"EC III",R75>0,"EC IV",Q75=TRUE,"EC V",S75<>"","SA"),"OK") -> IC III
A76: =A75+1 -> 75 | B76: Enhanced detection of fabricated news through sentiment analysis andtext feature extraction | C76: https://link.springer.com/article/10.1007/s41870-024-01971-2 | D76: 2024 | E76: 18 | F76: nan | G76: Google Scholar | H76: ['Comparison of methods'] | I76: =LEN(H76)-LEN(SUBSTITUTE(H76,",",""))+1 -> 1 | J76: TRUE | K76: TRUE | L76: FALSE | M76: TRUE | N76: FALSE | O76: FALSE | T76: =IFERROR(IFS(K76=FALSE,"IC III",L76=FALSE,"IC IV",M76=TRUE,"EC I",N76=TRUE,"EC II",O76=TRUE,"EC III",R76>0,"EC IV",Q76=TRUE,"EC V",S76<>"","SA"),"OK") -> IC IV
A77: =A76+1 -> 76 | B77: Enhancing Arabic‐text feature extractionutilizing label‐semantic augmentation in few/zero‐shot learning | C77: https://onlinelibrary.wiley.com/doi/abs/10.1111/exsy.13329 | D77: 2023 | E77: 16 | F77: https://onlinelibrary.wiley.com/doi/pdfdirect/10.1111/exsy.13329 | G77: Google Scholar | H77: ['Comparison of methods'] | I77: =LEN(H77)-LEN(SUBSTITUTE(H77,",",""))+1 -> 1 | J77: TRUE | K77: TRUE | L77: FALSE | M77: TRUE | N77: FALSE | O77: FALSE | T77: =IFERROR(IFS(K77=FALSE,"IC III",L77=FALSE,"IC IV",M77=TRUE,"EC I",N77=TRUE,"EC II",O77=TRUE,"EC III",R77>0,"EC IV",Q77=TRUE,"EC V",S77<>"","SA"),"OK") -> IC IV
A78: =A77+1 -> 77 | B78: Enhancing Emotion Detection in Textual Data: A Comparative Analysis of Machine Learning Models and Feature Extraction Techniques | C78: https://etasr.com/index.php/ETASR/article/view/7806 | D78: 2024 | E78: 5 | F78: https://etasr.com/index.php/ETASR/article/download/7806/3998 | G78: Google Scholar | H78: ['Classic Methods'] | I78: =LEN(H78)-LEN(SUBSTITUTE(H78,",",""))+1 -> 1 | J78: TRUE | K78: TRUE | L78: FALSE | M78: TRUE | N78: FALSE | O78: FALSE | T78: =IFERROR(IFS(K78=FALSE,"IC III",L78=FALSE,"IC IV",M78=TRUE,"EC I",N78=TRUE,"EC II",O78=TRUE,"EC III",R78>0,"EC IV",Q78=TRUE,"EC V",S78<>"","SA"),"OK") -> IC IV
A79: =A78+1 -> 78 | B79: Enhancing Emotion Detection in Textual Data: A Comparative Analysis of Machine Learning Models andFeature ExtractionTechniques | C79: https://etasr.com/index.php/ETASR/article/view/7806 | D79: 2024 | E79: 5 | F79: https://etasr.com/index.php/ETASR/article/download/7806/3998 | G79: Google Scholar | H79: ['Classic Methods'] | I79: =LEN(H79)-LEN(SUBSTITUTE(H79,",",""))+1 -> 1 | J79: TRUE | K79: TRUE | L79: FALSE | M79: TRUE | N79: FALSE | O79: FALSE | R79: 77 | T79: =IFERROR(IFS(K79=FALSE,"IC III",L79=FALSE,"IC IV",M79=TRUE,"EC I",N79=TRUE,"EC II",O79=TRUE,"EC III",R79>0,"EC IV",Q79=TRUE,"EC V",S79<>"","SA"),"OK") -> IC IV
A80: =A79+1 -> 79 | B80: Enhancing Text Classification Performance using Stacking Ensemble Method withTF-IDF Feature Extraction | C80: https://ieeexplore.ieee.org/abstract/document/10493890/ | D80: 2024 | E80: 12 | F80: nan | G80: Google Scholar | H80: ['Classic Methods'] | I80: =LEN(H80)-LEN(SUBSTITUTE(H80,",",""))+1 -> 1 | J80: TRUE | K80: TRUE | L80: FALSE | M80: TRUE | N80: FALSE | O80: FALSE | T80: =IFERROR(IFS(K80=FALSE,"IC III",L80=FALSE,"IC IV",M80=TRUE,"EC I",N80=TRUE,"EC II",O80=TRUE,"EC III",R80>0,"EC IV",Q80=TRUE,"EC V",S80<>"","SA"),"OK") -> IC IV
A81: =A80+1 -> 80 | B81: Enhancing hate speech detection with user characteristics | C81: https://link.springer.com/article/10.1007/s41060-023-00437-1 | D81: 2023 | E81: -1 | F81: None | G81: Springer International Journal of Data Science and Analytics | H81: ['Dense Embeddings', 'Contextual Embeddings', 'Comparison of methods'] | I81: =LEN(H81)-LEN(SUBSTITUTE(H81,",",""))+1 -> 3 | J81: TRUE | K81: TRUE | L81: FALSE | M81: TRUE | N81: FALSE | O81: FALSE | T81: =IFERROR(IFS(K81=FALSE,"IC III",L81=FALSE,"IC IV",M81=TRUE,"EC I",N81=TRUE,"EC II",O81=TRUE,"EC III",R81>0,"EC IV",Q81=TRUE,"EC V",S81<>"","SA"),"OK") -> IC IV
A82: =A81+1 -> 81 | B82: Enhancing misogyny detection in bilingual texts usingfasttextand explainable ai | C82: https://ieeexplore.ieee.org/abstract/document/10581058/ | D82: 2024 | E82: 13 | F82: https://drive.google.com/file/d/1XmiliiFtWYxtSEiQNjAAvaiomcysVpGg/view | G82: Google Scholar | H82: ['Dense Embeddings'] | I82: =LEN(H82)-LEN(SUBSTITUTE(H82,",",""))+1 -> 1 | J82: TRUE | K82: TRUE | L82: FALSE | M82: TRUE | N82: FALSE | O82: FALSE | T82: =IFERROR(IFS(K82=FALSE,"IC III",L82=FALSE,"IC IV",M82=TRUE,"EC I",N82=TRUE,"EC II",O82=TRUE,"EC III",R82>0,"EC IV",Q82=TRUE,"EC V",S82<>"","SA"),"OK") -> IC IV
A83: =A82+1 -> 82 | B83: Enhancing online toxicity detection on gaming networks: a novel embeddings-based valence lexicon approach | C83: https://link.springer.com/article/10.1007/s41060-025-00730-1 | D83: 2025 | E83: -1 | F83: None | G83: Springer International Journal of Data Science and Analytics | H83: ['Classic Methods', 'Dense Embeddings', 'Literature Reviews', 'Applied cases'] | I83: =LEN(H83)-LEN(SUBSTITUTE(H83,",",""))+1 -> 4 | J83: TRUE | K83: TRUE | L83: FALSE | M83: TRUE | N83: FALSE | O83: FALSE | T83: =IFERROR(IFS(K83=FALSE,"IC III",L83=FALSE,"IC IV",M83=TRUE,"EC I",N83=TRUE,"EC II",O83=TRUE,"EC III",R83>0,"EC IV",Q83=TRUE,"EC V",S83<>"","SA"),"OK") -> IC IV
A84: =A83+1 -> 83 | B84: Enhancing smart home device identification in WiFi environments for futuristic smart networks-based IoT | C84: https://link.springer.com/article/10.1007/s41060-023-00489-3 | D84: 2024 | E84: -1 | F84: None | G84: Springer International Journal of Data Science and Analytics | H84: ['Literature Reviews'] | I84: =LEN(H84)-LEN(SUBSTITUTE(H84,",",""))+1 -> 1 | J84: TRUE | K84: FALSE | L84: FALSE | M84: TRUE | N84: FALSE | O84: TRUE | T84: =IFERROR(IFS(K84=FALSE,"IC III",L84=FALSE,"IC IV",M84=TRUE,"EC I",N84=TRUE,"EC II",O84=TRUE,"EC III",R84>0,"EC IV",Q84=TRUE,"EC V",S84<>"","SA"),"OK") -> IC III
A85: =A84+1 -> 84 | B85: Enhancing textual relatedness assessment with combined transformers-embedding similarity techniques and machine learning regressors | C85: https://ieeexplore.ieee.org/abstract/document/10217726/ | D85: 2023 | E85: 3 | F85: https://www.researchgate.net/profile/Wael-Gomaa/publication/373375436_Enhancing_Textual_Relatedness_Assessment_with_Combined_Transformers-Embedding_Similarity_Techniques_and_Machine_Learning_Regressors/links/652bacdf0e4a1710e50ceddb/Enhancing-Textual-Relatedness-Assessment-with-Combined-Transformers-Embedding-Similarity-Techniques-and-Machine-Learning-Regressors.pdf | G85: Google Scholar | H85: ['Contextual Embeddings'] | I85: =LEN(H85)-LEN(SUBSTITUTE(H85,",",""))+1 -> 1 | J85: TRUE | K85: TRUE | L85: TRUE | M85: FALSE | N85: FALSE | O85: FALSE | P85: TRUE | Q85: FALSE | T85: =IFERROR(IFS(K85=FALSE,"IC III",L85=FALSE,"IC IV",M85=TRUE,"EC I",N85=TRUE,"EC II",O85=TRUE,"EC III",R85>0,"EC IV",Q85=TRUE,"EC V",S85<>"","SA"),"OK") -> OK
A86: =A85+1 -> 85 | B86: Evaluation ofTF-IDFExtraction Techniques in Sentiment Analysis of Indonesian-Language Marketplaces Using SVM, LogisticRegression, and Naive Bayes | C86: https://journal.unj.ac.id/unj/index.php/jkoma/article/view/60237 | D86: 2025 | E86: 2 | F86: https://journal.unj.ac.id/unj/index.php/jkoma/article/download/60237/21197 | G86: Google Scholar | H86: ['Classic Methods'] | I86: =LEN(H86)-LEN(SUBSTITUTE(H86,",",""))+1 -> 1 | J86: TRUE | K86: TRUE | L86: FALSE | M86: TRUE | N86: FALSE | O86: FALSE | T86: =IFERROR(IFS(K86=FALSE,"IC III",L86=FALSE,"IC IV",M86=TRUE,"EC I",N86=TRUE,"EC II",O86=TRUE,"EC III",R86>0,"EC IV",Q86=TRUE,"EC V",S86<>"","SA"),"OK") -> IC IV
A87: =A86+1 -> 86 | B87: Explainable hybrid word representations for sentiment analysis of financial news | C87: https://www.sciencedirect.com/science/article/pii/S0893608023001880 | D87: 2023 | E87: 34 | F87: https://opus.lib.uts.edu.au/bitstream/10453/171637/2/Explainable%20hybrid%20word%20representations%20for%20sentiment%20analysis%20of%20financial%20news.pdf | G87: Google Scholar | H87: ['Applied cases'] | I87: =LEN(H87)-LEN(SUBSTITUTE(H87,",",""))+1 -> 1 | J87: TRUE | K87: TRUE | L87: FALSE | M87: TRUE | N87: FALSE | O87: FALSE | T87: =IFERROR(IFS(K87=FALSE,"IC III",L87=FALSE,"IC IV",M87=TRUE,"EC I",N87=TRUE,"EC II",O87=TRUE,"EC III",R87>0,"EC IV",Q87=TRUE,"EC V",S87<>"","SA"),"OK") -> IC IV
A88: =A87+1 -> 87 | B88: Explainable long-sequence time-series forecasting for infectious diseases using optimised transformer models | C88: https://link.springer.com/article/10.1007/s41060-025-00930-9 | D88: 2025 | E88: -1 | F88: None | G88: Springer International Journal of Data Science and Analytics | H88: ['Literature Reviews'] | I88: =LEN(H88)-LEN(SUBSTITUTE(H88,",",""))+1 -> 1 | J88: TRUE | K88: FALSE | L88: TRUE | M88: FALSE | N88: TRUE | O88: FALSE | T88: =IFERROR(IFS(K88=FALSE,"IC III",L88=FALSE,"IC IV",M88=TRUE,"EC I",N88=TRUE,"EC II",O88=TRUE,"EC III",R88>0,"EC IV",Q88=TRUE,"EC V",S88<>"","SA"),"OK") -> IC III
A89: =A88+1 -> 88 | B89: Exploring machine learning-based methods for anomalies detection: evidence from cryptocurrencies | C89: https://link.springer.com/article/10.1007/s41060-024-00703-w | D89: 2024 | E89: -1 | F89: None | G89: Springer International Journal of Data Science and Analytics | H89: ['Applied cases'] | I89: =LEN(H89)-LEN(SUBSTITUTE(H89,",",""))+1 -> 1 | J89: TRUE | K89: FALSE | L89: FALSE | M89: TRUE | N89: TRUE | O89: FALSE | T89: =IFERROR(IFS(K89=FALSE,"IC III",L89=FALSE,"IC IV",M89=TRUE,"EC I",N89=TRUE,"EC II",O89=TRUE,"EC III",R89>0,"EC IV",Q89=TRUE,"EC V",S89<>"","SA"),"OK") -> IC III
A90: =A89+1 -> 89 | B90: Exploring the development of electrocatalysts through an automated comprehensiveliterature reviewusingNLP | C90: https://www.sciencedirect.com/science/article/pii/S2950284525000141 | D90: 2025 | E90: 1 | F90: https://papers.ssrn.com/sol3/Delivery.cfm?abstractid=5020756 | G90: Google Scholar | H90: ['Literature Reviews'] | I90: =LEN(H90)-LEN(SUBSTITUTE(H90,",",""))+1 -> 1 | J90: TRUE | K90: TRUE | L90: FALSE | M90: TRUE | N90: FALSE | O90: FALSE | T90: =IFERROR(IFS(K90=FALSE,"IC III",L90=FALSE,"IC IV",M90=TRUE,"EC I",N90=TRUE,"EC II",O90=TRUE,"EC III",R90>0,"EC IV",Q90=TRUE,"EC V",S90<>"","SA"),"OK") -> IC IV
A91: =A90+1 -> 90 | B91: FELIX: Automatic and interpretable feature engineering using llms | C91: https://link.springer.com/chapter/10.1007/978-3-031-70359-1_14 | D91: 2024 | E91: 8 | F91: nan | G91: Google Scholar | H91: ['Literature Reviews'] | I91: =LEN(H91)-LEN(SUBSTITUTE(H91,",",""))+1 -> 1 | J91: TRUE | K91: TRUE | L91: FALSE | M91: TRUE | N91: FALSE | O91: FALSE | T91: =IFERROR(IFS(K91=FALSE,"IC III",L91=FALSE,"IC IV",M91=TRUE,"EC I",N91=TRUE,"EC II",O91=TRUE,"EC III",R91>0,"EC IV",Q91=TRUE,"EC V",S91<>"","SA"),"OK") -> IC IV
A92: =A91+1 -> 91 | B92: FRP-TNN: an intelligent framework using transformer for financial market risk prediction to enhance decision-making under uncertainty | C92: https://link.springer.com/article/10.1007/s41060-025-00873-1 | D92: 2025 | E92: -1 | F92: None | G92: Springer International Journal of Data Science and Analytics | H92: ['Dense Embeddings', 'Literature Reviews', 'Applied cases'] | I92: =LEN(H92)-LEN(SUBSTITUTE(H92,",",""))+1 -> 3 | J92: TRUE | K92: TRUE | L92: FALSE | M92: TRUE | N92: FALSE | O92: FALSE | T92: =IFERROR(IFS(K92=FALSE,"IC III",L92=FALSE,"IC IV",M92=TRUE,"EC I",N92=TRUE,"EC II",O92=TRUE,"EC III",R92>0,"EC IV",Q92=TRUE,"EC V",S92<>"","SA"),"OK") -> IC IV
A93: =A92+1 -> 92 | B93: Fake news detection: deep semantic representation with enhanced feature engineering | C93: https://link.springer.com/article/10.1007/s41060-023-00387-8 | D93: 2023 | E93: -1 | F93: None | G93: Springer International Journal of Data Science and Analytics | H93: ['Classic Methods', 'Dense Embeddings', 'Literature Reviews', 'Applied cases'] | I93: =LEN(H93)-LEN(SUBSTITUTE(H93,",",""))+1 -> 4 | J93: TRUE | K93: TRUE | L93: FALSE | M93: TRUE | N93: FALSE | O93: FALSE | T93: =IFERROR(IFS(K93=FALSE,"IC III",L93=FALSE,"IC IV",M93=TRUE,"EC I",N93=TRUE,"EC II",O93=TRUE,"EC III",R93>0,"EC IV",Q93=TRUE,"EC V",S93<>"","SA"),"OK") -> IC IV
A94: =A93+1 -> 93 | B94: Feature selection based on the complexity of structural patterns in RDF graphs | C94: https://link.springer.com/article/10.1007/s41060-023-00466-w | D94: 2023 | E94: -1 | F94: None | G94: Springer International Journal of Data Science and Analytics | H94: ['Dense Embeddings'] | I94: =LEN(H94)-LEN(SUBSTITUTE(H94,",",""))+1 -> 1 | J94: TRUE | K94: TRUE | L94: FALSE | M94: TRUE | N94: FALSE | O94: FALSE | T94: =IFERROR(IFS(K94=FALSE,"IC III",L94=FALSE,"IC IV",M94=TRUE,"EC I",N94=TRUE,"EC II",O94=TRUE,"EC III",R94>0,"EC IV",Q94=TRUE,"EC V",S94<>"","SA"),"OK") -> IC IV
A95: =A94+1 -> 94 | B95: Financial distress prediction with annual reports-based deep textual feature extraction: A hybrid approach | C95: https://www.sciencedirect.com/science/article/pii/S0020025524012325 | D95: 2025 | E95: 14 | F95: nan | G95: Google Scholar | H95: ['Applied cases'] | I95: =LEN(H95)-LEN(SUBSTITUTE(H95,",",""))+1 -> 1 | J95: TRUE | K95: TRUE | L95: FALSE | M95: TRUE | N95: FALSE | O95: FALSE | T95: =IFERROR(IFS(K95=FALSE,"IC III",L95=FALSE,"IC IV",M95=TRUE,"EC I",N95=TRUE,"EC II",O95=TRUE,"EC III",R95>0,"EC IV",Q95=TRUE,"EC V",S95<>"","SA"),"OK") -> IC IV
A96: =A95+1 -> 95 | B96: Forecasting Scientific Impact: A Model for Predicting Citation Counts | C96: http://iapress.org/index.php/soic/article/view/2524 | D96: 2025 | E96: 1 | F96: http://iapress.org/index.php/soic/article/download/2524/1365 | G96: Google Scholar | H96: ['General'] | I96: =LEN(H96)-LEN(SUBSTITUTE(H96,",",""))+1 -> 1 | J96: TRUE | K96: TRUE | L96: TRUE | M96: FALSE | N96: FALSE | O96: FALSE | P96: TRUE | Q96: FALSE | T96: =IFERROR(IFS(K96=FALSE,"IC III",L96=FALSE,"IC IV",M96=TRUE,"EC I",N96=TRUE,"EC II",O96=TRUE,"EC III",R96>0,"EC IV",Q96=TRUE,"EC V",S96<>"","SA"),"OK") -> OK
A97: =A96+1 -> 96 | B97: Fourier transform and permutation-based transformer for drug–target binding affinity prediction | C97: https://link.springer.com/article/10.1007/s41060-025-00865-1 | D97: 2025 | E97: -1 | F97: None | G97: Springer International Journal of Data Science and Analytics | H97: ['Applied cases'] | I97: =LEN(H97)-LEN(SUBSTITUTE(H97,",",""))+1 -> 1 | J97: TRUE | K97: TRUE | L97: FALSE | M97: TRUE | N97: FALSE | O97: FALSE | T97: =IFERROR(IFS(K97=FALSE,"IC III",L97=FALSE,"IC IV",M97=TRUE,"EC I",N97=TRUE,"EC II",O97=TRUE,"EC III",R97>0,"EC IV",Q97=TRUE,"EC V",S97<>"","SA"),"OK") -> IC IV
A98: =A97+1 -> 97 | B98: From embeddings to equations: Genetic-programming surrogates for interpretable transformer classification | C98: https://arxiv.org/abs/2509.21341 | D98: 2025 | E98: 1 | F98: https://arxiv.org/pdf/2509.21341? | G98: Google Scholar | H98: ['Contextual Embeddings'] | I98: =LEN(H98)-LEN(SUBSTITUTE(H98,",",""))+1 -> 1 | J98: TRUE | K98: TRUE | L98: FALSE | M98: TRUE | N98: FALSE | O98: FALSE | T98: =IFERROR(IFS(K98=FALSE,"IC III",L98=FALSE,"IC IV",M98=TRUE,"EC I",N98=TRUE,"EC II",O98=TRUE,"EC III",R98>0,"EC IV",Q98=TRUE,"EC V",S98<>"","SA"),"OK") -> IC IV
A99: =A98+1 -> 98 | B99: GViG: low-resource generative visual grounding using prompt-based language modeling for visual question answering | C99: https://link.springer.com/article/10.1007/s41060-025-00835-7 | D99: 2025 | E99: -1 | F99: None | G99: Springer International Journal of Data Science and Analytics | H99: ['Comparison of methods'] | I99: =LEN(H99)-LEN(SUBSTITUTE(H99,",",""))+1 -> 1 | J99: TRUE | K99: TRUE | L99: FALSE | M99: TRUE | N99: FALSE | O99: FALSE | T99: =IFERROR(IFS(K99=FALSE,"IC III",L99=FALSE,"IC IV",M99=TRUE,"EC I",N99=TRUE,"EC II",O99=TRUE,"EC III",R99>0,"EC IV",Q99=TRUE,"EC V",S99<>"","SA"),"OK") -> IC IV
A100: =A99+1 -> 99 | B100: Graph neural networks: Historical backgrounds, present revolutions, and conventionalization for the future | C100: https://link.springer.com/article/10.1007/s41060-025-00797-w | D100: 2025 | E100: -1 | F100: None | G100: Springer International Journal of Data Science and Analytics | H100: ['Dense Embeddings'] | I100: =LEN(H100)-LEN(SUBSTITUTE(H100,",",""))+1 -> 1 | J100: TRUE | K100: TRUE | L100: FALSE | M100: TRUE | N100: TRUE | O100: FALSE | T100: =IFERROR(IFS(K100=FALSE,"IC III",L100=FALSE,"IC IV",M100=TRUE,"EC I",N100=TRUE,"EC II",O100=TRUE,"EC III",R100>0,"EC IV",Q100=TRUE,"EC V",S100<>"","SA"),"OK") -> IC IV
...

Sheet 3_Dados
A1: Identificação
A2: ID
A3: Código do artigo (ex: A01, A02). | B3: Ano de publicação (filtro: $\geq$ 2023). | C3: Nome completo do trabalho. | D3: Google Scholar ou IJDSA. | E3: URL | F3: Nacionalidade Autores | G3: Revista | H3: Idioma Dataset | I3: Domínio | J3: Target | K3: Embeddings | L3: Estratégia | M3: Tunning | N3: Classe modelo | O3: Tamanho Dataset | P3: Métricas | Q3: Vantagens | R3: Limitações | S3: Contribuições | T3: Ganho Relativo ao Baseline
A4: 1 | B4: 2024 | C4: Adequate Prompting Improves Performance of Regression Models of Emotional Content | D4: Google Scholar | E4: =VLOOKUP(C4,'2_Prisma'!B:C,2,0) -> https://dl.acm.org/doi/abs/10.1145/3677525.3678653 | F4: Italy | G4: Association for Computing Machinery | H4: English, Italian | I4: Psychology | J4: VAD | K4: Contextual | L4: Sentence | M4: Fine-Tuning | N4: Deep Learning & Neural Networks | O4: "10548", "10062" | P4: Pearson Correlation | Q4: Does not require an exclusive dataset, Better metrics | R4: Transparency | S4: Methodological Application, Fine-tuning | T4: =AVERAGE(0.844/0.838,0.587/0.573,0.539/0.536)-1 -> 0.012396576
A5: =A4+1 -> 2 | B5: 2023 | C5: Dating Greek papyri withtext regression | D5: Google Scholar | E5: =VLOOKUP(C5,'2_Prisma'!B:C,2,0) -> https://aclanthology.org/2023.acl-long.556/ | F5: Greece, Sweeden, Switzerland, Italy | G5: Association for Computational Linguistics | H5: Greek | I5: Palaeography | J5: Century of document | K5: Classical | L5: Token, Sentence | M5: Fine-Tuning | N5: Linear & Statistical Models, Tree-Based & Ensemble Models | O5: "389" | P5: MAE, MSE, R² | Q5: Human effort reduction, Novel Use Case | R5: Data loss, Data Quality, Data Availability | S5: Dataset/Resource, Methodological Application | T5: =AVERAGE(1/(0.54/0.91),1/(1.17/1.91),84.64/76.59)-1 -> 0.47425631
A6: =A5+1 -> 3 | B6: 2023 | C6: Designing a forecasting assistant of the Bitcoin price based on deep learning using market sentiment analysis and multiple feature extraction | D6: Google Scholar | E6: =VLOOKUP(C6,'2_Prisma'!B:C,2,0) -> https://link.springer.com/article/10.1007/s00500-023-09028-5 | F6: Iran | G6: Springer Soft Computing | H6: English | I6: Finance | J6: Bitcoin Closing Price of Next Day | K6: Hybrid | L6: Token, Document | M6: Fine-Tuning | N6: Deep Learning & Neural Networks, Deep Learning (Sequential, Recurrent, & Attention) | O6: "1200000" | P6: R², MSE, RMSE, MedAE | Q6: Better metrics | R6: Lack of benchmarks, Lack of transparency | S6: Multimodal Integration | T6: 0
A7: =A6+1 -> 4 | B7: 2024 | C7: Investigation of graph-based clustering approaches along with graph neural networks for modeling armed conflict in Bangladesh | D7: Springer International Journal of Data Science and Analytics | E7: =VLOOKUP(C7,'2_Prisma'!B:C,2,0) -> https://link.springer.com/article/10.1007/s41060-024-00572-3 | F7: Bangladesh | G7: Springer International Journal of Data Science and Analytics | H7: English | I7: Political Science | J7: Fatality Count | K7: Hybrid | L7: Token | M7: Fine-Tuning | N7: Deep Learning & Neural Networks | O7: "13383" | P7: R², MSE, RMSE | Q7: Captures relational dependencies, Performs well with reduced features or sparse data | R7: Computational Complexity, Sensibility to Biases, Data Dimensionality | S7: Methodological Application | T7: =AVERAGE(0.86/0.92)-1 -> -0.065217391 | U7: The model with 93% R² is in a distinct setup | Only gives R² for final model
A8: =A7+1 -> 5 | B8: 2023 | C8: Embeddingregression: Models for context-specific description and inference | D8: Google Scholar | E8: =VLOOKUP(C8,'2_Prisma'!B:C,2,0) -> https://www.cambridge.org/core/journals/american-political-science-review/article/embedding-regression-models-for-contextspecific-description-and-inference/4C90013E5C714C8483ED95CC699022FB | F8: United States | G8: American Political Science Review | H8: English | I8: Political Science | J8: Embedding Vector | K8: Hybrid | L8: Token | M8: Frozen | N8: Linear & Statistical Models | O8: "400", "71" | P8: Cluster Homogeneity, Cosine Similarity, Coefficient Norm | Q8: Sample Efficiency, Speed, Transparency | R8: Assumption of Stability, Data Availability, Pretraining Dependence | S8: New Framework, Domain Insight | T8: 0
A9: =A8+1 -> 6 | B9: 2023 | C9: Enhancing textual relatedness assessment with combined transformers-embedding similarity techniques and machine learning regressors | D9: Google Scholar | E9: =VLOOKUP(C9,'2_Prisma'!B:C,2,0) -> https://ieeexplore.ieee.org/abstract/document/10217726/ | F9: Egypt | G9: Intelligent Methods, Systems, and Applications (IMSA) | H9: English | I9: Natural Language Processing | J9: Relatedness Score | K9: Contextual | L9: Sentence | M9: Frozen | N9: Linear & Statistical Models, Tree-Based & Ensemble Models, Deep Learning & Neural Networks, Instance-Based & Kernel Methods | O9: "9840" | P9: Pearson Correlation, Spearman Correlation, MSE | Q9: Better metrics, Generalize Better | R9: Lack of transparency, Computational Complexity | S9: Feature Engineering | T9: =AVERAGE(1/(0.04809249/0.20241),0.978/0.8969,0.9696/0.8404)-1 -> 1.1509747
A10: =A9+1 -> 7 | B10: 2025 | C10: Forecasting Scientific Impact: A Model for Predicting Citation Counts | D10: Google Scholar | E10: =VLOOKUP(C10,'2_Prisma'!B:C,2,0) -> http://iapress.org/index.php/soic/article/view/2524 | F10: Vietnam | G10: Statistics, Optimization & Information Computing | H10: English | I10: Bibliometrics | J10: Paper Citation Count | K10: Dense | L10: Token | M10: Fine-Tuning | N10: Linear & Statistical Models, Tree-Based & Ensemble Models, Deep Learning & Neural Networks, Deep Learning (Sequential, Recurrent, & Attention) | O10: "1296" | P10: RMSE | Q10: Better Metrics | R10: Sensibility to Biases, Computational Complexity, Data Availability | S10: Methodological Application | T10: =AVERAGE(1/(7.25/11.8))-1 -> 0.62758621
A11: =A10+1 -> 8 | B11: 2025 | C11: Video sentiment analysis on social media using an advanced VADER technique | D11: Springer International Journal of Data Science and Analytics | E11: =VLOOKUP(C11,'2_Prisma'!B:C,2,0) -> https://link.springer.com/article/10.1007/s41060-025-00849-1 | F11: India, Cyprus | G11: Springer International Journal of Data Science and Analytics | H11: English, Hinglish | I11: Social Media | J11: Sentiment Intensity | K11: Hybrid | L11: Sentence | M11: Fine-Tuning | N11: Lexicon / Rule-Based Models | O11: "32800" | P11: MAE, MSE, R² | Q11: Transparency, Speed, Handles slang/emojis/informal text better | R11: Sensibility to Biases, Necessity of Manual Tunning | S11: Feature Engineering, New Pipeline | T11: 0 | U11: No baseline for comparsion in regression
A12: =A11+1 -> 9 | B12: 2025 | C12: A novel sentiment correlation-based method with dual transformer model for stock price prediction | D12: Springer International Journal of Data Science and Analytics | E12: =VLOOKUP(C12,'2_Prisma'!B:C,2,0) -> https://link.springer.com/article/10.1007/s41060-025-00932-7 | F12: Japan | G12: Springer International Journal of Data Science and Analytics | H12: English | I12: Finance | J12: Next day's closing price | K12: Contextual | L12: Document | M12: Fine-Tuning | N12: Deep Learning & Neural Networks | O12: "24000" | P12: MSE | Q12: Captures relational dependencies, Handle Missings | R12: Data Availability, Sensibility to Biases, Necessity of Manual Tunning | S12: New Architecture, Multimodal Integration | T12: =1/AVERAGE(0.002/0.032,0.004/0.029,0.018/0.035,0.032/0.034,0.022/0.037,0.041/0.043,0.032/0.064,0.029/0.038,0.026/0.044,0.022/0.028,0.023/0.041,0.031/0.048,0.009/0.027,0.01/0.026,0.028/0.043,0.035/0.063)-1 -> 0.78268343 | U12: Mean for individual results
A13: =A12+1 -> 10 | B13: 2023 | C13: Read the news, not the books: forecasting firms' long-term financial performance via deep text mining | D13: Google Scholar | E13: =VLOOKUP(C13,'2_Prisma'!B:C,2,0) -> https://dl.acm.org/doi/abs/10.1145/3533018 | F13: United States | G13: Association for Computing Machinery | H13: English | I13: Finance | J13: Companie's Key Financial Indicators | K13: Hybrid | L13: Sentence | M13: Frozen | N13: Traditional Time Series & Econometrics, Deep Learning (Sequential, Recurrent, & Attention) | O13: "778669" | P13: MAPE | Q13: Better metrics, Adaptability, Problem Independent, Transparency | R13: Reliability on Data Quality, Model Can be Optimized, Not Tested on Broader Environmentes | S13: Exploratory Analysis
A14: =A13+1 -> 11 | B14: 2026 | C14: SentiVol-GA: a volatility-scaled genetic fusion of predictive models and financial sentiment for adaptive stock forecasting | D14: Springer International Journal of Data Science and Analytics | E14: =VLOOKUP(C14,'2_Prisma'!B:C,2,0) -> https://link.springer.com/article/10.1007/s41060-025-00983-w | F14: India | G14: Springer International Journal of Data Science and Analytics | H14: English | I14: Finance | J14: Next day's closing price | K14: Hybrid | L14: Sentence | M14: Frozen | N14: Linear & Statistical Models, Tree-Based & Ensemble Models, Deep Learning (Sequential, Recurrent, & Attention), Traditional Time Series & Econometrics | O14: "1250" | P14: R², RMSE, MAE, MSE, Tolerance-Based Accuracy | Q14: Adaptability, Generalization, Better metrics, Transparency | R14: Computational Complexity, Reliability on Data Quality, Complex Design | S14: New Framework, Multimodal Integration
A15: =A14+1 -> 12 | B15: 2023 | C15: Regression applied to legal judgments to predict compensation for immaterial damage | D15: Google Scholar | E15: =VLOOKUP(C15,'2_Prisma'!B:C,2,0) -> https://peerj.com/articles/cs-1225/ | F15: Brazil | G15: PeerJ Computer Science | H15: Brazilian Portuguese | I15: Legal | J15: Monetary value of compensation for immaterial damage | K15: Classical | L15: Document | M15: Frozen | N15: Linear & Statistical Models, Tree-Based & Ensemble Models, Deep Learning & Neural Networks, Instance-Based & Kernel Methods | O15: "928" | P15: R², RMSE, MAE | Q15: Human effort reduction, Better metrics, Novel Use Case | R15: Small Dataset Size | S15: New Framework, Feature Engineering | T15: =AVERAGE(1/(2.464/3.276),1/(1.813/2.596),0.49/0.11,1/(1.812/2.908),1/(890/1.997),0.72/0.3,1/(2.274/3.842),1/(972/2.38),0.56/-0.23,1/(2.355/2.968),1/(1.601/2.27),0.53/0.27,1/(1.75/2.784),1/(915/2.006),0.74/0.36,1/(1.94/2.902),1/(879/2.122),0.68/0.3,1/(2.157/3.031),1/(1.399/2.273),0.61/0.24,1/(1.837/2.914),1/(939/2.004),0.71/0.3,1/(2.423/3.276),1/(1.758/2.445),0.5/0.11,1/(3.54/3.553),1/(2.714/2.75),-0.05/-0.04,1/(1.807/2.912),1/(847/2.059),0.72/0.3)-1 -> 0.41305433
A16: =A15+1 -> 13 | B16: 2025 | C16: Regression in EO: Are VLMs Up to the Challenge? | D16: Google Scholar | E16: =VLOOKUP(C16,'2_Prisma'!B:C,2,0) -> https://arxiv.org/abs/2502.14088 | F16: Germany | G16: arXiv Preprint | H16: English | I16: Geoscience | J16: Continuous geophysical/environmental variables | K16: Contextual | L16: Token | M16: Fine-Tuning | N16: Deep Learning & Neural Networks | P16: N/A | Q16: Transparency, Better Reasoning | R16: Lack of Benchmarks, Cumulative Error Accumulation, Conflict Between Discrete and Continuous Representations | S16: Exploratory Analysis | T16: 0
A17: =A16+1 -> 14 | B17: 2023 | C17: Text Regression Analysis for Predictive Intervals Using Gradient Boosting | D17: Google Scholar | E17: =VLOOKUP(C17,'2_Prisma'!B:C,2,0) -> https://link.springer.com/chapter/10.1007/978-3-031-28073-3_18 | F17: Bulgaria, Germany | G17: Advances in Information and Communication
A18: =A17+1 -> 15 | B18: 2023 | C18: Text‐based soybean futures price forecasting: A two‐stage deep learning approach | D18: Google Scholar | E18: =VLOOKUP(C18,'2_Prisma'!B:C,2,0) -> https://onlinelibrary.wiley.com/doi/abs/10.1002/for.2909 | F18: China | G18: Journal of Forecasting | H18: Chinese | I18: Finance | J18: Soybean Futures Price | K18: Hybrid | L18: Document | M18: Frozen | N18: Deep Learning (Sequential, Recurrent, & Attention) | O18: "795" | P18: MSE, RMSE, MAE, MAPE, SMAPE | Q18: Better Metrics | R18: Data Scope | S18: New Architecture | T18: =AVERAGE(1/(0.008/0.01),1/(0.094/0.102),1/(0.068/0.084),1/(5.891/8.716),1/(6.141/9.875),1/(0.058/0.059))-1 -> 0.27920521 | U18: TSH-LSTM against best for each metric
A19: =A18+1 -> 16 | B19: 2025 | C19: Short and Long-Term Renewable Electricity Demand Forecasting Based on CNN-Bi-GRU Model | D19: Google Scholar | E19: =VLOOKUP(C19,'2_Prisma'!B:C,2,0) -> https://www.icck.org/article/tetai/193/143 | F19: United States | G19: ICCK Transactions on Emerging Topics in Artificial Intelligence | H19: Chinese | I19: Energy | J19: Renewable electricity generation/supply | K19: Hybrid | L19: Token | M19: Frozen | N19: Deep Learning (Sequential, Recurrent, & Attention) | O19: "11342" | P19: RMSE, MAPE, Dstat | Q19: Better metrics, Handle nonlinear and dynamic factors | R19: Transparency, Computational Complexity, Sensibility to Biases, Data Quality | S19: New Architecture, Multimodal Integration | T19: =AVERAGE(1/(6/8),1/(146/220),82/79)-1 -> 0.29271911
A20: =A19+1 -> 17 | B20: 2024 | C20: Text regressionanalysis: A review, empirical, and experimental insights | D20: Google Scholar | E20: =VLOOKUP(C20,'2_Prisma'!B:C,2,0) -> https://ieeexplore.ieee.org/abstract/document/10640097/ | F20: United Arab Emirates | G20: IEEE Access | H20: English (Inferred from dataset sources like Amazon/Yelp/Boston/UCI). | I20: Multidisciplinary | J20: Sentiment scores (reviews), Median home value (housing), Heating/Cooling loads (energy). | K20: Classical | L20: Document | M20: NA | N20: Linear & Statistical Models | O20: "2000000", "8000000", "506", "768" | P20: RMSE | Q20: Better Metrics, Handle Multicolinearity | R20: Data Scope | S20: Systematic Evaluation | T20: 0
A21: =A20+1 -> 18 | B21: 2023 | C21: Interpretable deep learning based textregressionfor financial prediction | D21: Google Scholar | E21: =VLOOKUP(C21,'2_Prisma'!B:C,2,0) -> https://onlinelibrary.wiley.com/doi/abs/10.1111/exsy.13368 | F21: China | G21: Expert Systems | H21: Chinese | I21: Finance | J21: Company ROA | K21: Contextual | L21: Document | M21: Fine-Tuning | N21: Deep Learning & Neural Networks, Deep Learning (Sequential, Recurrent, & Attention) | O21: "594" | P21: MAE, Spearman Correlation | Q21: Novel Use Case, Captures Dynamic Semantic Changes | R21: Reliability on Data Quality | S21: New Architecture | T21: =AVERAGE(1/(1.4736/1.64),0.764/0.6843)-1 -> 0.11469506
A22: =A21+1 -> 19 | B22: 2024 | C22: The effects of sentiment evolution in financial texts: A word embedding approach | D22: Google Scholar | E22: =VLOOKUP(C22,'2_Prisma'!B:C,2,0) -> https://www.tandfonline.com/doi/abs/10.1080/07421222.2023.2301176 | F22: Hong Kong | G22: Journal of Management Information Systems | H22: English | I22: Finance | J22: Excess stock return, Future earnings, Fraud indicator | K22: Dense | L22: Token | M22: Frozen (Embeddings trained yearly on corpus, then used to calculate static intensity scores for regression) | N22: Linear & Statistical Models | O22: "199176", "194928"; "6372781" | P22: Adjusted R², Pseudo R², Coefficients, t-statistics | Q22: Captures Dynamic Semantic Changes, Combines Human Domain Knowledge with Machine Learning, Transparency, Better Metrics | R22: Ignores Data Dependence, Data Scope | S22: New Framework, Domain Insight
A23: =A22+1 -> 20 | B23: 2024 | C23: SMPDF: stock movement prediction based on stock prices and text | D23: Google Scholar | E23: =VLOOKUP(C23,'2_Prisma'!B:C,2,0) -> https://www.tandfonline.com/doi/abs/10.1080/03081079.2023.2294132 | F23: China | G23: International Journal of General Systems
A24: =A23+1 -> 21 | B24: 2024 | C24: [HTML]Enhancing Agile Story Point Estimation: Integrating Deep Learning, Machine Learning, and Natural Language Processing with SBERT and Gradient Boosted … | D24: Google Scholar | E24: =VLOOKUP(C24,'2_Prisma'!B:C,2,0) -> https://www.mdpi.com/2076-3417/14/16/7305 | F24: Türkiye, Australia | G24: Applied Sciences | H24: English | I24: IT | J24: Story Points of Issue Task | K24: Contextual | L24: Documents | M24: Frozen | N24: Tree-Based & Ensemble Models | O24: "31960" | P24: MAE, MdAE, SA | Q24: Better metrics | R24: Data Scope, Model Can be Optimized | S24: Methodological Application, Feature Engineering | T24: 0.12 | U24: On MAE (pg. 3)
A25: =A24+1 -> 22 | B25: 2023 | C25: [HTML]Item difficulty prediction using itemtext features:Comparisonof predictive performance across machine-learning algorithms | D25: Google Scholar | E25: =VLOOKUP(C25,'2_Prisma'!B:C,2,0) -> https://www.mdpi.com/2227-7390/11/19/4104 | F25: Czech Republic | G25: Mathematics | H25: English | I25: Psychology | J25: Item Dificulty | K25: Hybrid | L25: Token (Lemmatized Word) | M25: Fine-Tuning | N25: Linear & Statistical Models, Tree-Based & Ensemble Models, Deep Learning & Neural Networks, Instance-Based & Kernel Methods | O25: "40" | P25: RMSE | Q25: Better metrics, Mathematical Rigor | R25: Small dataset, Conflict Between Discrete and Continuous Representations | S25: Methodological Application | T25: =AVERAGE(1/(0.694/1.004))-1 -> 0.44668588 | U25: RMSE against domain experts
A26: =A25+1 -> 23 | B26: 2025 | C26: [HTML]Using natural language processing to track negative emotions in the daily lives of adolescents | D26: Google Scholar | E26: =VLOOKUP(C26,'2_Prisma'!B:C,2,0) -> https://pmc.ncbi.nlm.nih.gov/articles/PMC12047991/ | F26: United States | G26: NLM Preprint | H26: English | I26: Psychology | J26: Sadness, Anger, Nervousness | K26: Hybrid | L26: Document | M26: Frozen | N26: Linear & Statistical Models, Tree-Based & Ensemble Models | O26: "7680" | P26: R², RMSE | Q26: Better metrics | R26: Modest Overall Predictive Accuracy, Necessity of Large Datasets, Transparency, Data Scope | S26: Methodological Application, Domain Insight | T26: =AVERAGE(0.38/0.17,0.33/0.14,0.2/0.13,0.24/0.11,0.1/0.11,0.1/0.09,0.09/0.07,0.06/0.07,0.1/0.1,0.1/0.1,0.06/0.07,0.08/0.09,1/(0.55/0.64),1/(0.75/0.85),1/(0.69/0.72),1/(0.85/0.92),1/(0.52/0.61),1/(0.73/0.82),1/(0.63/0.88),1/(0.81/0.88),1/(0.47/0.48),1/(0.68/0.69),1/(0.64/0.66),1/(0.75/0.76))-1 -> 0.229366 | U26: Random Forest against Elastic Net
A27: =A26+1 -> 24 | B27: 2025 | C27: [PDF]Financial Market Prediction using Contrastive Learning-based News Representation and Multi-Resolution Market Data | D27: Google Scholar | E27: =VLOOKUP(C27,'2_Prisma'!B:C,2,0) -> https://assets.pubpub.org/p41eo02p/119-01746737674155.pdf | F27: Canada, Iran | G27: The 38th Canadian Conference on Artificial Intelligence | H27: English | I27: Finance | J27: Next day's closing price | K27: Contextual | L27: Sentence, Document | M27: Frozen | N27: Linear & Statistical Models, Deep Learning (Sequential, Recurrent, & Attention) | O27: "7872" | P27: MAPE | Q27: Better metrics, Use of AoE embeddings | R27: Non-stationarity, Sensibility to Biases | S27: New Architecture, Multimodal Integration | T27: =1/AVERAGE(1.058/1.145,1.072/1.161,0.866/0.866,3.273/3.367)-1 -> 0.047273566 | U27: In test
A28: =A27+1 -> 25 | B28: 2023 | C28: [PDF]The implementation ofglovetext embeddings and numerical indicators analysis for plastic resin price prediction | D28: Google Scholar | E28: =VLOOKUP(C28,'2_Prisma'!B:C,2,0) -> http://www.icicel.org/ell/contents/2023/3/el-17-03-01.pdf | F28: Thailand | G28: ICIC Express Letters | H28: English | I28: Industrial | J28: Plastic Resin Price | K28: Dense | L28: Token | M28: Frozen | N28: Traditional Time Series & Econometrics | O28: "371" | P28: RMSE, Test Loss | Q28: Better metrics | R28: Small Dataset Size, Data Quality | S28: New Architecture, Multimodal Integration | T28: 0 | U28: Doesn't have baselines
A29: =A28+1 -> 26 | B29: 2024 | C29: … SemEval-2024 Task 1: Evaluating Semantic Textual Relatedness in Low-resource Languages using Various Embedding Methods and Machine LearningRegression… | D29: Google Scholar | E29: =VLOOKUP(C29,'2_Prisma'!B:C,2,0) -> https://aclanthology.org/2024.semeval-1.65/ | F29: Mexico | G29: Association for Computational Linguistics | H29: Algerian Arabic, Amharic, Hausa, Kinyarwanda, Moroccan Arabic, Marathi, Telugu, Spanish, and English | I29: Natural Language Processing | J29: Semantic Relatedness Score | K29: Hybrid | L29: Sentence | M29: Frozen | N29: Linear & Statistical Models, Tree-Based & Ensemble Models, Deep Learning & Neural Networks, Instance-Based & Kernel Methods | O29: "7795" | P29: Spearman correlation | Q29: Better metrics | R29: Linguistic Ambiguities, Cultural Nuances, Data Availability | S29: Systematic Evaluation | T29: 0 | U29: Doesn't have baselines

Sheet 4_WordCloud
A1: Identificação
A2: ID
A3: Código do artigo (ex: A01, A02). | B3: Ano de publicação (filtro: $\geq$ 2023). | C3: Nome completo do trabalho. | D3: Google Scholar ou IJDSA. | E3: URL | F3: Abstract
A4: 1 | B4: 2024 | C4: Adequate Prompting Improves Performance of Regression Models of Emotional Content | D4: Google Scholar | E4: =VLOOKUP(C4,'2_Prisma'!B:C,2,0) -> https://dl.acm.org/doi/abs/10.1145/3677525.3678653 | F4: Regression models of natural language content are widely popular in many applications, such as sentiment analysis, stance detection and emotion detection. The multidimensional Russell and Mehrabian’s Valence-Arousal-Dominance (VAD) model has been universally recognized as a valuable tool for describing emotional content. Standard methods for VAD prediction learn the relation between natural language text and VAD values by fine-tuning a pre-trained machine learning model based on Transformers (e.g. BERT) on a corpus of natural language sentences manually annotated with VAD. We investigate the potential of employing effective prompting, a technique previously proven to be advantageous in classification and other natural language processing (NLP) tasks, to enhance the VAD prediction process. Our findings reveal that with appropriate prompting, we can leverage the knowledge acquired during pre-training to improve regression performance, showcasing the benefits of this approach for VAD prediction.
A5: =A4+1 -> 2 | B5: 2023 | C5: Dating Greek papyri withtext regression | D5: Google Scholar | E5: =VLOOKUP(C5,'2_Prisma'!B:C,2,0) -> https://aclanthology.org/2023.acl-long.556/ | F5: Dating Greek papyri accurately is crucial not only to edit their texts but also to understand numerous other aspects of ancient writing, document and book production and circulation, as well as various other aspects of administration, everyday life and intellectual history of antiquity. Although a substantial number of Greek papyri documents bear a date or other conclusive data as to their chronological placement, an even larger number can only be dated tentatively or in approximation, due to the lack of decisive evidence. By creating a dataset of 389 transcriptions of documentary Greek papyri, we train 389 regression models and we predict a date for the papyri with an average MAE of 54 years and an MSE of 1.17, outperforming image classifiers and other baselines. Last, we release date estimations for 159 manuscripts, for which only the upper limit is known.
A6: =A5+1 -> 3 | B6: 2023 | C6: Designing a forecasting assistant of the Bitcoin price based on deep learning using market sentiment analysis and multiple feature extraction | D6: Google Scholar | E6: =VLOOKUP(C6,'2_Prisma'!B:C,2,0) -> https://link.springer.com/article/10.1007/s00500-023-09028-5 | F6: Nowadays, the issue of fluctuations in the price of digital Bitcoin currency has a striking impact on the profit or loss of people, international relations, and trade. Accordingly, designing a model that can take into account the various significant factors for predicting the Bitcoin price with the highest accuracy is essential. Hence, the current paper uses market sentiment and multiple feature extraction to present several Bitcoin price prediction models based on convolutional neural network and long short-term memory. In the proposed models, several parameters, including Twitter data, news headlines, news content, Google Trends, Bitcoin-based stock, and finance, are employed based on deep learning to make a more accurate prediction. Such parameters are the input data used to predict the Bitcoin price. Besides, the proposed model analyzes the Valence Aware Dictionary and Sentiment Reasoner sentiments to examine the market’s latest news and cryptocurrencies. According to this study’s various inputs and analyses, several effective feature selection methods, including mutual information regression, linear regression, correlation-based, and a combination of the feature selection models, are exploited to predict the price of Bitcoin. Finally, a careful comparison is made between the proposed models in terms of some performance criteria like mean square error (MSE), root-mean-square error, mean absolute error, median absolute error, and coefficient of determination (R2). The obtained results indicate that the proposed hybrid model based on sentiments analysis and combined feature selection with MSE value of 0.001 and R2 value of 0.98 provides better estimations with more minor errors regarding Bitcoin price. This proposed model can also be employed as an individual assistant for more informed trading decisions associated with Bitcoin.
A7: =A6+1 -> 4 | B7: 2024 | C7: Investigation of graph-based clustering approaches along with graph neural networks for modeling armed conflict in Bangladesh | D7: Springer International Journal of Data Science and Analytics | E7: =VLOOKUP(C7,'2_Prisma'!B:C,2,0) -> https://link.springer.com/article/10.1007/s41060-024-00572-3 | F7: Determining fatality rates—a critical component of conflict analysis and comprehending the dynamics of armed conflict in Bangladesh are the main goals of this study. The contributions of this paper are twofold. Firstly, this paper presents the performance of graph neural networks (GNNs) is measured against traditional machine learning (ML) algorithms, specifically artificial neural networks (ANNs), for fatality prediction. Secondly, it has presented an empirical analysis of graph-based clustering and traditional clustering methods for modeling armed conflicts in Bangladesh. Predictive fatality models have been developed using graph neural networks and traditional machine learning algorithms. Graph neural networks exploit the graph structure of the data, allowing for more effective modeling and prediction. Traditional machine learning algorithms, and artificial neural networks, serve as benchmarks for comparison. The results indicate that graph-based clustering methods provide valuable insights into the structure and dynamics of armed conflicts in Bangladesh. The comparative analysis demonstrates that graph neural networks outperform a few traditional machine learning algorithms in terms of predictive fatality, highlighting the importance of capturing the relational dependencies present in the data. Graph-based clustering techniques offer an innovative approach by capturing the inherent relational structure of conflicting data, whereas traditional clustering methods rely on traditional feature engineering and distance metrics. A comprehensive dataset from ACLED for armed conflict incidents in Bangladesh was used to evaluate the performance. Both graph-based and traditional clustering methods were applied to identify meaningful clusters and analyze the patterns of armed conflict. An additional contribution has been made through the construction and analysis of a knowledge graph, elucidating the interconnected relationships among various datasets. In conclusion, this research contributes to the field of conflict analysis by showcasing the advantages of graph-based clustering methods and graph neural networks for understanding armed conflict patterns and predicting fatality rates.
A8: =A7+1 -> 5 | B8: 2023 | C8: Embeddingregression: Models for context-specific description and inference | D8: Google Scholar | E8: =VLOOKUP(C8,'2_Prisma'!B:C,2,0) -> https://www.cambridge.org/core/journals/american-political-science-review/article/embedding-regression-models-for-contextspecific-description-and-inference/4C90013E5C714C8483ED95CC699022FB | F8: Social scientists commonly seek to make statements about how word use varies over circumstances—including time, partisan identity, or some other document-level covariate. For example, researchers might wish to know how Republicans and Democrats diverge in their understanding of the term “immigration.” Building on the success of pretrained language models, we introduce the à la carte on text (conText) embedding regression model for this purpose. This fast and simple method produces valid vector representations of how words are used—and thus what words “mean”—in different contexts. We show that it outperforms slower, more complicated alternatives and works well even with very few documents. The model also allows for hypothesis testing and statements about statistical significance. We demonstrate that it can be used for a broad range of important tasks, including understanding US polarization, historical legislative development, and sentiment detection. We provide open-source software for fitting the model.
A9: =A8+1 -> 6 | B9: 2023 | C9: Enhancing textual relatedness assessment with combined transformers-embedding similarity techniques and machine learning regressors | D9: Google Scholar | E9: =VLOOKUP(C9,'2_Prisma'!B:C,2,0) -> https://ieeexplore.ieee.org/abstract/document/10217726/ | F9: In natural language processing (NLP), accurately calculating relatedness scores between pairs of sentences has significant implications for various tasks, such as information retrieval and document clustering. To improve relatedness score calculation, this study employed a two-layered approach. Firstly, embedding similarity techniques were utilized, leveraging seven different transformers to obtain vectors for each pair of sentences. Secondly, a classical machine learning regressor was trained on these seven vectors. The combination of these methods resulted in state-of-the-art performance on a standard dataset named SICK, with a mean square error of 0.0481, and Pearson’s and Spearman’s correlations of 0.978 and 0.9696, respectively. This research highlights the potential of combining embedding similarity techniques with machine learning methods to enhance relatedness score assessment and other NLP tasks, ultimately contributing to the advancement of NLP algorithms and their applications.
A10: =A9+1 -> 7 | B10: 2025 | C10: Forecasting Scientific Impact: A Model for Predicting Citation Counts | D10: Google Scholar | E10: =VLOOKUP(C10,'2_Prisma'!B:C,2,0) -> http://iapress.org/index.php/soic/article/view/2524 | F10: Forecasting the citation counts of scientific papers is a challenging task, particularly when utilizing textual data such as author names, paper titles, abstracts, and affiliations. This task diverges from conventional regression problems involving numerical or categorical inputs, as it demands the processing of complex, high-dimensional text features. Traditional regression techniques, including Linear Regression, Polynomial Regression, and Decision Tree Regression, often fail to encapsulate the semantic intricacies of textual data and are susceptible to overfitting due to the expansive feature space. In the context of Vietnam, where research output is rapidly growing yet underexplored in predictive modeling, these limitations are especially pronounced. To tackle these issues, we leverage advanced Natural Language Processing (NLP) techniques, employing Long Short-Term Memory (LSTM) and Gated Recurrent Unit (GRU) networks. These deep learning models are adept at handling sequential data, capturing long-range dependencies, and preserving contextual nuances, rendering them well-suited for text-based citation prediction. We conducted experiments using a dataset of academicpapers authored by Vietnamese researchers across diverse disciplines, sourced from publications featuring Vietnamese author contributions. The dataset includes features such as author names, titles, abstracts, and affiliations, reflecting the unique characteristics of Vietnam’s research landscape. We compared the performance of LSTM and GRU models against traditional machine learning approaches, evaluating prediction accuracy with metrics like Mean Absolute Error (MAE) and Root Mean Squared Error (RMSE). The results reveal that LSTM and GRU models substantially outperform their traditional counterparts. The LSTM model achieved an RMSE of 8.54 and an MAE of 8.1, while the GRU model yielded an RMSE of 8.32 and an MAE of 7.83, demonstrating robust predictive capabilities. In contrast, traditional models such as Decision Tree Regression and Linear Regression exhibited higher error rates, with RMSEs exceeding 12.0. These findings underscore the efficacy of deep learning in forecasting citation counts from textual data, particularly for Vietnamese research outputs, and highlight the potential of LSTM and GRU models to uncover intricate patterns driving scientific impact in emerging research ecosystems.
A11: =A10+1 -> 8 | B11: 2025 | C11: Video sentiment analysis on social media using an advanced VADER technique | D11: Springer International Journal of Data Science and Analytics | E11: =VLOOKUP(C11,'2_Prisma'!B:C,2,0) -> https://link.springer.com/article/10.1007/s41060-025-00849-1 | F11: Manually gaging public sentiment in the millions of informal, multilingual comments posted on social media vlogs is infeasible, and existing models often falter on slang, code-switching, emojis, and rapid shifts in tone. To address this challenge, we compile a 36 000-comment corpus drawn from India’s most-viewed channels on YouTube, Twitter (X), TikTok, Reddit, Instagram, and Facebook, then build an end-to-end Python NLP pipeline that blends deep learning–based preprocessing (tokenization, misspelling correction, code-mix detection) with an enhanced version of VADER (Valence Aware Dictionary for Sentiment Reasoning). The lexicon is augmented with 276 domain-specific slang terms and emojis, and custom rules capture sarcasm, negation, and intensity cues. The upgraded VADER attains an F1-score of 1.00 on the in-sample corpus and 0.92 on an external hold-out set, surpassing fine-tuned BERT (F1 = 0.94) and zero-shot GPT 3.5 (F1 = 0.91). Regression metrics (MAE = 1.4, MSE = 3.1, ) confirm precise sentiment intensity estimation, while temporal analysis reveals highly polarized reactions within the first 24 h that converge toward neutrality over time. Content-type analysis shows strong positivity for technology and fashion vlogs (51–57%) but 61% disapproval for travel content. Overall, the framework generalizes across comedic, scientific, and satirical contexts (36.8% positive, 57.3% neutral) and offers a transparent, scalable solution for real-time sentiment monitoring in multilingual social media environments
A12: =A11+1 -> 9 | B12: 2025 | C12: A novel sentiment correlation-based method with dual transformer model for stock price prediction | D12: Springer International Journal of Data Science and Analytics | E12: =VLOOKUP(C12,'2_Prisma'!B:C,2,0) -> https://link.springer.com/article/10.1007/s41060-025-00932-7 | F12: In real-world financial markets, a company’s stock performance is often influenced by its competitors, partners, and other connected firms. However, traditional sentiment-based approaches typically focus only on the target company’s sentiment, overlooking the broader network of influence. To address this limitation, this paper proposes a Dual Transformer architecture that integrates sentiment signals from connected companies to enhance prediction accuracy. This approach aims to bridge a critical gap in financial sentiment analysis by capturing inter-company relationships and their impact on stock price movements. The Dual Transformer comprises two transformer structures, the Enhancement Transformer and the Forecast Transformer. The Enhancement Transformer is used to enhance the correlation strengths between related companies, while the Forecast Transformer is used for stock price forecasting. Eight companies from various industries and financial markets are selected for analysis. The model utilizes the polarity scores of these related companies, combined with historical closing prices from 2015 to 2024, to forecast the next day’s closing price. Prediction performance is evaluated using the mean squared error (MSE). Experimental results demonstrate that incorporating the news sentiment of related companies improves the prediction of the target company’s stock price when using the proposed Dual Transformer model. In addition, the Dual Transformer model can outperform existing models such as Temporal Fusion Transformer, N-Beats, Informer, and LSTM by achieving consistently lower MSE values across all eight companies.
A13: =A12+1 -> 10 | B13: 2023 | C13: Read the news, not the books: forecasting firms' long-term financial performance via deep text mining | D13: Google Scholar | E13: =VLOOKUP(C13,'2_Prisma'!B:C,2,0) -> https://dl.acm.org/doi/abs/10.1145/3533018 | F13: In this paper, we show textual data from firm-related events in news articles can effectively predict various firm financial ratios, with or without historical financial ratios. We exploit state-of-the-art neural architectures, including pseudo-event embeddings, Long Short-Term Memory Networks, and attention mechanisms. Our news-powered deep learning models are shown to outperform standard econometric models operating on precise accounting historical data. We also observe forecasting quality improvement when integrating textual and numerical data streams. In addition, we provide in-depth case studies for model explainability and transparency. Our forecasting models, model attention maps, and firm embeddings benefit various stakeholders with quality predictions and explainable insights. Our proposed models can be applied both when numerically historical data is or is not available
A14: =A13+1 -> 11 | B14: 2026 | C14: SentiVol-GA: a volatility-scaled genetic fusion of predictive models and financial sentiment for adaptive stock forecasting | D14: Springer International Journal of Data Science and Analytics | E14: =VLOOKUP(C14,'2_Prisma'!B:C,2,0) -> https://link.springer.com/article/10.1007/s41060-025-00983-w | F14: SentiVol-GA is an evolvable hybrid framework for stock price forecasting. This model integrates statistical models, deep learning architectures, financial sentiment analysis, and volatility-aware optimization through a Genetic Algorithm (GA). This framework combines five predictive models—Linear Regression, LSTM, GRU, Bi-LSTM, and ARIMA—with sentiment signals extracted from FinBERT, VADER, and the Loughran–McDonald dictionary. Its core innovation lies in a volatility-scaling mechanism that adjusts sentiment impact during turbulent periods, while the GA periodically optimizes model and sentiment weights to minimize forecasting error thus sustaining the model’s predictive stability. This empirical evaluation across eight Indian IT-sector stocks—covering large, mid- and small-cap segments, demonstrates up to 12% improvement in R2, 30–60% reduction in RMSE, and 20–35% gain in tolerance-based accuracy over classical and deep-learning baselines. Nonparametric Friedman and Wilcoxon tests (p < 0.05) confirm that these performance gains are statistically significant. SentiVol-GA offers a volatility-aware, sentiment-driven, and dynamically optimized approach that is scalable, interpretable, and robust for intelligent financial decision-making.
A15: =A14+1 -> 12 | B15: 2023 | C15: Regression applied to legal judgments to predict compensation for immaterial damage | D15: Google Scholar | E15: =VLOOKUP(C15,'2_Prisma'!B:C,2,0) -> https://peerj.com/articles/cs-1225/ | F15: Immaterial damage compensation is a controversial matter in the judicial practice of several law systems. Due to a lack of criteria for its assessment, the judge is free to establish the value based on his/her conviction. Our research motivation is that knowing the estimated amount of immaterial damage compensation at the initial stage of a lawsuit can encourage an agreement between the parties. We thus investigate text regression techniques to predict the compensation value from legal judgments in which consumers had problems with airlines and claim for immaterial damage. We start from a simple pipeline and create others by adding some natural language processing (NLP) and machine learning (ML) techniques, which we call adjustments. The adjustments include N-Grams Extraction, Feature Selection, Overfitting Avoidance, Cross-Validation and Outliers Removal. An special adjustment, Addition of Attributes Extracted by the Legal Expert (AELE), is proposed as a complementary input to the case text. We evaluate the impact of adding these adjustments in the pipeline in terms of prediction quality and execution time. N-Grams Extraction and Addition of AELE have the biggest impact on the prediction quality. In terms of execution time, Feature Selection and Overfitting Avoidance have significant importance. Moreover, we notice the existence of pipelines with subsets of adjustments that achieved better prediction quality than a pipeline with them all. The result is promising since the prediction error of the best pipeline is acceptable in the legal environment. Consequently, the predictions will likely be helpful in a legal environment.
A16: =A15+1 -> 13 | B16: 2025 | C16: Regression in EO: Are VLMs Up to the Challenge? | D16: Google Scholar | E16: =VLOOKUP(C16,'2_Prisma'!B:C,2,0) -> https://arxiv.org/abs/2502.14088 | F16: Earth Observation (EO) data encompass a vast range of remotely sensed information, featuring multi-sensor and multi-temporal, playing an indispensable role in understanding our planet's dynamics. Recently, Vision Language Models (VLMs) have achieved remarkable success in perception and reasoning tasks, bringing new insights and opportunities to the EO field. However, the potential for EO applications, especially for scientific regression related applications remains largely unexplored. This paper bridges that gap by systematically examining the challenges and opportunities of adapting VLMs for EO regression tasks. The discussion first contrasts the distinctive properties of EO data with conventional computer vision datasets, then identifies four core obstacles in applying VLMs to EO regression: 1) the absence of dedicated benchmarks, 2) the discrete-versus-continuous representation mismatch, 3) cumulative error accumulation, and 4) the suboptimal nature of text-centric training objectives for numerical tasks. Next, a series of methodological insights and potential subtle pitfalls are explored. Lastly, we offer some promising future directions for designing robust, domain-aware solutions. Our findings highlight the promise of VLMs for scientific regression in EO, setting the stage for more precise and interpretable modeling of critical environmental processes.
... A29: =A28+1 -> 26 | B29: 2024 | C29: … SemEval-2024 Task 1: Evaluating Semantic Textual Relatedness in Low-resource Languages using Various Embedding Methods and Machine LearningRegression… | D29: Google Scholar | E29: =VLOOKUP(C29,'2_Prisma'!B:C,2,0) -> https://aclanthology.org/2024.semeval-1.65/ | F29: In this paper, I describe my submission to the SemEval-2024 contest. I tackled subtask 1 - “Semantic Textual Relatedness for African and Asian Languages”. To find the semantic relatedness of sentence pairs, I tackled this task by creating models for nine different languages. I then vectorized the text data using a variety of embedding techniques including doc2vec, tf-idf, Sentence-Transformers, Bert, Roberta, and more, and used 11 traditional machine learning techniques of the regression type for analysis and evaluation.
